{
  "model_name": "distilbert-base-uncased",
  "dataset": "IEMOCAP_Final",
  "experiment_type": "multimodal",
  "epochs": 40,
  "batch_size": 32,
  "train_samples": 7025,
  "val_samples": 1506,
  "test_samples": 1506,
  "epoch_logs": [
    {
      "epoch": 1,
      "train_steps": [
        {
          "step": 22,
          "loss": 8.024023056030273
        },
        {
          "step": 44,
          "loss": 6.904064178466797
        },
        {
          "step": 66,
          "loss": 5.561064720153809
        },
        {
          "step": 88,
          "loss": 5.229288101196289
        },
        {
          "step": 110,
          "loss": 3.9790515899658203
        },
        {
          "step": 132,
          "loss": 4.123358726501465
        },
        {
          "step": 154,
          "loss": 3.5347659587860107
        },
        {
          "step": 176,
          "loss": 3.0930423736572266
        },
        {
          "step": 198,
          "loss": 2.0359437465667725
        },
        {
          "step": 220,
          "loss": 1.8369669914245605
        }
      ],
      "val_loss": 1.3348818520704906,
      "val_accuracy": 0.7330236295859018,
      "train_loss": 4.843779915571213
    },
    {
      "epoch": 2,
      "train_steps": [
        {
          "step": 22,
          "loss": 1.3544650077819824
        },
        {
          "step": 44,
          "loss": 1.2483861446380615
        },
        {
          "step": 66,
          "loss": 1.1656872034072876
        },
        {
          "step": 88,
          "loss": 1.0857117176055908
        },
        {
          "step": 110,
          "loss": 1.187081217765808
        },
        {
          "step": 132,
          "loss": 0.8549340963363647
        },
        {
          "step": 154,
          "loss": 1.1008342504501343
        },
        {
          "step": 176,
          "loss": 1.1570537090301514
        },
        {
          "step": 198,
          "loss": 1.1000871658325195
        },
        {
          "step": 220,
          "loss": 1.0476423501968384
        }
      ],
      "val_loss": 0.6141656866918007,
      "val_accuracy": 0.8771668626616399,
      "train_loss": 1.1336521742018786
    },
    {
      "epoch": 3,
      "train_steps": [
        {
          "step": 22,
          "loss": 0.8771330714225769
        },
        {
          "step": 44,
          "loss": 1.1019015312194824
        },
        {
          "step": 66,
          "loss": 0.9828323125839233
        },
        {
          "step": 88,
          "loss": 1.0194798707962036
        },
        {
          "step": 110,
          "loss": 0.8844282031059265
        },
        {
          "step": 132,
          "loss": 1.0035054683685303
        },
        {
          "step": 154,
          "loss": 0.9538711309432983
        },
        {
          "step": 176,
          "loss": 1.1422200202941895
        },
        {
          "step": 198,
          "loss": 0.7939912676811218
        },
        {
          "step": 220,
          "loss": 1.3540805578231812
        }
      ],
      "val_loss": 0.5606182739138603,
      "val_accuracy": 0.8878763452172279,
      "train_loss": 0.9431593789295717
    },
    {
      "epoch": 4,
      "train_steps": [
        {
          "step": 22,
          "loss": 0.7146798968315125
        },
        {
          "step": 44,
          "loss": 1.2178452014923096
        },
        {
          "step": 66,
          "loss": 0.8134564757347107
        },
        {
          "step": 88,
          "loss": 0.8443357944488525
        },
        {
          "step": 110,
          "loss": 0.9660207629203796
        },
        {
          "step": 132,
          "loss": 0.6016628742218018
        },
        {
          "step": 154,
          "loss": 0.8870866298675537
        },
        {
          "step": 176,
          "loss": 0.7134024500846863
        },
        {
          "step": 198,
          "loss": 0.9171966314315796
        },
        {
          "step": 220,
          "loss": 0.8708620667457581
        }
      ],
      "val_loss": 0.501021628578504,
      "val_accuracy": 0.8997956742842992,
      "train_loss": 0.8545599027113481
    },
    {
      "epoch": 5,
      "train_steps": [
        {
          "step": 22,
          "loss": 0.6545990705490112
        },
        {
          "step": 44,
          "loss": 0.5024312138557434
        },
        {
          "step": 66,
          "loss": 0.8605022430419922
        },
        {
          "step": 88,
          "loss": 0.7439678907394409
        },
        {
          "step": 110,
          "loss": 0.7700120806694031
        },
        {
          "step": 132,
          "loss": 0.5368766784667969
        },
        {
          "step": 154,
          "loss": 1.0662649869918823
        },
        {
          "step": 176,
          "loss": 0.8469283580780029
        },
        {
          "step": 198,
          "loss": 0.9140087962150574
        },
        {
          "step": 220,
          "loss": 0.9791185259819031
        }
      ],
      "val_loss": 0.4864715492973725,
      "val_accuracy": 0.9027056901405255,
      "train_loss": 0.7820999890565872
    },
    {
      "epoch": 6,
      "train_steps": [
        {
          "step": 22,
          "loss": 0.6894130706787109
        },
        {
          "step": 44,
          "loss": 0.6716732978820801
        },
        {
          "step": 66,
          "loss": 0.5466822385787964
        },
        {
          "step": 88,
          "loss": 0.6152985095977783
        },
        {
          "step": 110,
          "loss": 0.740092933177948
        },
        {
          "step": 132,
          "loss": 0.8257918357849121
        },
        {
          "step": 154,
          "loss": 0.705501914024353
        },
        {
          "step": 176,
          "loss": 0.7323217391967773
        },
        {
          "step": 198,
          "loss": 0.6040074229240417
        },
        {
          "step": 220,
          "loss": 0.6681556701660156
        }
      ],
      "val_loss": 0.44950679689645767,
      "val_accuracy": 0.9100986406207084,
      "train_loss": 0.7020339697599411
    },
    {
      "epoch": 7,
      "train_steps": [
        {
          "step": 22,
          "loss": 0.5841070413589478
        },
        {
          "step": 44,
          "loss": 0.6110398769378662
        },
        {
          "step": 66,
          "loss": 0.6528452634811401
        },
        {
          "step": 88,
          "loss": 0.5308128595352173
        },
        {
          "step": 110,
          "loss": 0.6004918813705444
        },
        {
          "step": 132,
          "loss": 0.5923957228660583
        },
        {
          "step": 154,
          "loss": 0.9428872466087341
        },
        {
          "step": 176,
          "loss": 0.8706367015838623
        },
        {
          "step": 198,
          "loss": 0.8873045444488525
        },
        {
          "step": 220,
          "loss": 0.5912110209465027
        }
      ],
      "val_loss": 0.43931308947503567,
      "val_accuracy": 0.9121373821049928,
      "train_loss": 0.6609190004793081
    },
    {
      "epoch": 8,
      "train_steps": [
        {
          "step": 22,
          "loss": 0.5764609575271606
        },
        {
          "step": 44,
          "loss": 0.49526914954185486
        },
        {
          "step": 66,
          "loss": 0.4646494388580322
        },
        {
          "step": 88,
          "loss": 0.5973833799362183
        },
        {
          "step": 110,
          "loss": 0.8319703936576843
        },
        {
          "step": 132,
          "loss": 0.6479334235191345
        },
        {
          "step": 154,
          "loss": 0.44143611192703247
        },
        {
          "step": 176,
          "loss": 0.45622310042381287
        },
        {
          "step": 198,
          "loss": 0.6936875581741333
        },
        {
          "step": 220,
          "loss": 0.6436111330986023
        }
      ],
      "val_loss": 0.43286246806383133,
      "val_accuracy": 0.9134275063872337,
      "train_loss": 0.6188024993647229
    },
    {
      "epoch": 9,
      "train_steps": [
        {
          "step": 22,
          "loss": 0.6001788973808289
        },
        {
          "step": 44,
          "loss": 0.4727371633052826
        },
        {
          "step": 66,
          "loss": 0.5910581946372986
        },
        {
          "step": 88,
          "loss": 0.541837751865387
        },
        {
          "step": 110,
          "loss": 0.5444871783256531
        },
        {
          "step": 132,
          "loss": 0.5345691442489624
        },
        {
          "step": 154,
          "loss": 0.43982213735580444
        },
        {
          "step": 176,
          "loss": 0.744530200958252
        },
        {
          "step": 198,
          "loss": 0.7218264937400818
        },
        {
          "step": 220,
          "loss": 0.588456392288208
        }
      ],
      "val_loss": 0.45168713356057805,
      "val_accuracy": 0.9096625732878844,
      "train_loss": 0.5849646346135573
    },
    {
      "epoch": 10,
      "train_steps": [
        {
          "step": 22,
          "loss": 0.5379143953323364
        },
        {
          "step": 44,
          "loss": 0.614802360534668
        },
        {
          "step": 66,
          "loss": 0.8020755648612976
        },
        {
          "step": 88,
          "loss": 0.5590249300003052
        },
        {
          "step": 110,
          "loss": 0.6545883417129517
        },
        {
          "step": 132,
          "loss": 0.6361774206161499
        },
        {
          "step": 154,
          "loss": 0.7092294096946716
        },
        {
          "step": 176,
          "loss": 0.45886072516441345
        },
        {
          "step": 198,
          "loss": 0.44533976912498474
        },
        {
          "step": 220,
          "loss": 0.5599875450134277
        }
      ],
      "val_loss": 0.45044085135062534,
      "val_accuracy": 0.9099118297298749,
      "train_loss": 0.5632203614169901
    },
    {
      "epoch": 11,
      "train_steps": [
        {
          "step": 22,
          "loss": 0.5600466132164001
        },
        {
          "step": 44,
          "loss": 0.5348554253578186
        },
        {
          "step": 66,
          "loss": 0.5653549432754517
        },
        {
          "step": 88,
          "loss": 0.49643850326538086
        },
        {
          "step": 110,
          "loss": 0.5976267457008362
        },
        {
          "step": 132,
          "loss": 0.40684938430786133
        },
        {
          "step": 154,
          "loss": 0.7078156471252441
        },
        {
          "step": 176,
          "loss": 0.5966953039169312
        },
        {
          "step": 198,
          "loss": 0.365143746137619
        },
        {
          "step": 220,
          "loss": 0.6286227703094482
        }
      ],
      "val_loss": 0.4356647872676452,
      "val_accuracy": 0.912867042546471,
      "train_loss": 0.5302272399718111
    },
    {
      "epoch": 12,
      "train_steps": [
        {
          "step": 22,
          "loss": 0.6500961184501648
        },
        {
          "step": 44,
          "loss": 0.42539846897125244
        },
        {
          "step": 66,
          "loss": 0.423832505941391
        },
        {
          "step": 88,
          "loss": 0.5016347765922546
        },
        {
          "step": 110,
          "loss": 0.544376015663147
        },
        {
          "step": 132,
          "loss": 0.6169750690460205
        },
        {
          "step": 154,
          "loss": 0.4454185366630554
        },
        {
          "step": 176,
          "loss": 0.6659020781517029
        },
        {
          "step": 198,
          "loss": 0.4924832284450531
        },
        {
          "step": 220,
          "loss": 0.3518727123737335
        }
      ],
      "val_loss": 0.4556057887772719,
      "val_accuracy": 0.9088788422445456,
      "train_loss": 0.506829531761733
    },
    {
      "epoch": 13,
      "train_steps": [
        {
          "step": 22,
          "loss": 0.6335592865943909
        },
        {
          "step": 44,
          "loss": 0.49259036779403687
        },
        {
          "step": 66,
          "loss": 0.5832582712173462
        },
        {
          "step": 88,
          "loss": 0.5208367109298706
        },
        {
          "step": 110,
          "loss": 0.5411087274551392
        },
        {
          "step": 132,
          "loss": 0.5605746507644653
        },
        {
          "step": 154,
          "loss": 0.4620906114578247
        },
        {
          "step": 176,
          "loss": 0.516770601272583
        },
        {
          "step": 198,
          "loss": 0.5059095621109009
        },
        {
          "step": 220,
          "loss": 0.4915144145488739
        }
      ],
      "val_loss": 0.45736393208305043,
      "val_accuracy": 0.90852721358339,
      "train_loss": 0.49065774530172346
    },
    {
      "epoch": 14,
      "train_steps": [
        {
          "step": 22,
          "loss": 0.4579734802246094
        },
        {
          "step": 44,
          "loss": 0.47535228729248047
        },
        {
          "step": 66,
          "loss": 0.48928511142730713
        },
        {
          "step": 88,
          "loss": 0.45060938596725464
        },
        {
          "step": 110,
          "loss": 0.5155436396598816
        },
        {
          "step": 132,
          "loss": 0.5667046308517456
        },
        {
          "step": 154,
          "loss": 0.5379990339279175
        },
        {
          "step": 176,
          "loss": 0.4766828417778015
        },
        {
          "step": 198,
          "loss": 0.5499500036239624
        },
        {
          "step": 220,
          "loss": 0.45843058824539185
        }
      ],
      "val_loss": 0.45670175304015476,
      "val_accuracy": 0.9086596493919691,
      "train_loss": 0.4756802879951217
    },
    {
      "epoch": 15,
      "train_steps": [
        {
          "step": 22,
          "loss": 0.5059788227081299
        },
        {
          "step": 44,
          "loss": 0.3783118724822998
        },
        {
          "step": 66,
          "loss": 0.4988710880279541
        },
        {
          "step": 88,
          "loss": 0.3965960443019867
        },
        {
          "step": 110,
          "loss": 0.4324783682823181
        },
        {
          "step": 132,
          "loss": 0.4762963652610779
        },
        {
          "step": 154,
          "loss": 0.5433520674705505
        },
        {
          "step": 176,
          "loss": 0.48827308416366577
        },
        {
          "step": 198,
          "loss": 0.46905380487442017
        },
        {
          "step": 220,
          "loss": 0.5374256372451782
        }
      ],
      "val_loss": 0.45752127282321453,
      "val_accuracy": 0.908495745435357,
      "train_loss": 0.4563930553468791
    },
    {
      "epoch": 16,
      "train_steps": [
        {
          "step": 22,
          "loss": 0.34891557693481445
        },
        {
          "step": 44,
          "loss": 0.5448548197746277
        },
        {
          "step": 66,
          "loss": 0.45702630281448364
        },
        {
          "step": 88,
          "loss": 0.5636878609657288
        },
        {
          "step": 110,
          "loss": 0.2944924831390381
        },
        {
          "step": 132,
          "loss": 0.48335570096969604
        },
        {
          "step": 154,
          "loss": 0.4162191152572632
        },
        {
          "step": 176,
          "loss": 0.42554888129234314
        },
        {
          "step": 198,
          "loss": 0.4946204423904419
        },
        {
          "step": 220,
          "loss": 0.3324940800666809
        }
      ],
      "val_loss": 0.45857722871005535,
      "val_accuracy": 0.9082845542579889,
      "train_loss": 0.4370968535542488
    },
    {
      "epoch": 17,
      "train_steps": [
        {
          "step": 22,
          "loss": 0.43469172716140747
        },
        {
          "step": 44,
          "loss": 0.4208100736141205
        },
        {
          "step": 66,
          "loss": 0.34163016080856323
        },
        {
          "step": 88,
          "loss": 0.3389059901237488
        },
        {
          "step": 110,
          "loss": 0.3353593051433563
        },
        {
          "step": 132,
          "loss": 0.4727616310119629
        },
        {
          "step": 154,
          "loss": 0.4904167056083679
        },
        {
          "step": 176,
          "loss": 0.5308849215507507
        },
        {
          "step": 198,
          "loss": 0.35859888792037964
        },
        {
          "step": 220,
          "loss": 0.34686005115509033
        }
      ],
      "val_loss": 0.4616779287656148,
      "val_accuracy": 0.907664414246877,
      "train_loss": 0.41865516250783746
    },
    {
      "epoch": 18,
      "train_steps": [
        {
          "step": 22,
          "loss": 0.4639257788658142
        },
        {
          "step": 44,
          "loss": 0.3716757297515869
        },
        {
          "step": 66,
          "loss": 0.4697955548763275
        },
        {
          "step": 88,
          "loss": 0.4226617217063904
        },
        {
          "step": 110,
          "loss": 0.3601841926574707
        },
        {
          "step": 132,
          "loss": 0.47127556800842285
        },
        {
          "step": 154,
          "loss": 0.6496300101280212
        },
        {
          "step": 176,
          "loss": 0.4454248547554016
        },
        {
          "step": 198,
          "loss": 0.5214006304740906
        },
        {
          "step": 220,
          "loss": 0.31948480010032654
        }
      ],
      "val_loss": 0.4707441510011752,
      "val_accuracy": 0.905851169799765,
      "train_loss": 0.4056764761155302
    },
    {
      "epoch": 19,
      "train_steps": [
        {
          "step": 22,
          "loss": 0.5740213990211487
        },
        {
          "step": 44,
          "loss": 0.4653542935848236
        },
        {
          "step": 66,
          "loss": 0.4056640863418579
        },
        {
          "step": 88,
          "loss": 0.3202574849128723
        },
        {
          "step": 110,
          "loss": 0.2891780734062195
        },
        {
          "step": 132,
          "loss": 0.5139716267585754
        },
        {
          "step": 154,
          "loss": 0.38624686002731323
        },
        {
          "step": 176,
          "loss": 0.2831803560256958
        },
        {
          "step": 198,
          "loss": 0.4178493916988373
        },
        {
          "step": 220,
          "loss": 0.3266739249229431
        }
      ],
      "val_loss": 0.47781405101219815,
      "val_accuracy": 0.9044371897975604,
      "train_loss": 0.3954367962750522
    },
    {
      "epoch": 20,
      "train_steps": [
        {
          "step": 22,
          "loss": 0.39697226881980896
        },
        {
          "step": 44,
          "loss": 0.434547483921051
        },
        {
          "step": 66,
          "loss": 0.3764486014842987
        },
        {
          "step": 88,
          "loss": 0.35301899909973145
        },
        {
          "step": 110,
          "loss": 0.3201739490032196
        },
        {
          "step": 132,
          "loss": 0.4697134494781494
        },
        {
          "step": 154,
          "loss": 0.3240385949611664
        },
        {
          "step": 176,
          "loss": 0.3492007255554199
        },
        {
          "step": 198,
          "loss": 0.40975433588027954
        },
        {
          "step": 220,
          "loss": 0.32188650965690613
        }
      ],
      "val_loss": 0.4620584174990654,
      "val_accuracy": 0.9075883165001869,
      "train_loss": 0.38149826790798796
    },
    {
      "epoch": 21,
      "train_steps": [
        {
          "step": 22,
          "loss": 0.3715939223766327
        },
        {
          "step": 44,
          "loss": 0.36062806844711304
        },
        {
          "step": 66,
          "loss": 0.30896592140197754
        },
        {
          "step": 88,
          "loss": 0.38276487588882446
        },
        {
          "step": 110,
          "loss": 0.4240952432155609
        },
        {
          "step": 132,
          "loss": 0.32378408312797546
        },
        {
          "step": 154,
          "loss": 0.37942296266555786
        },
        {
          "step": 176,
          "loss": 0.3826388120651245
        },
        {
          "step": 198,
          "loss": 0.28345370292663574
        },
        {
          "step": 220,
          "loss": 0.5676356554031372
        }
      ],
      "val_loss": 0.5027330095569292,
      "val_accuracy": 0.8994533980886141,
      "train_loss": 0.37564843107353557
    },
    {
      "epoch": 22,
      "train_steps": [
        {
          "step": 22,
          "loss": 0.32954931259155273
        },
        {
          "step": 44,
          "loss": 0.38936278223991394
        },
        {
          "step": 66,
          "loss": 0.392986536026001
        },
        {
          "step": 88,
          "loss": 0.3857770562171936
        },
        {
          "step": 110,
          "loss": 0.46444129943847656
        },
        {
          "step": 132,
          "loss": 0.2873210310935974
        },
        {
          "step": 154,
          "loss": 0.3333451449871063
        },
        {
          "step": 176,
          "loss": 0.37330543994903564
        },
        {
          "step": 198,
          "loss": 0.34740516543388367
        },
        {
          "step": 220,
          "loss": 0.19843727350234985
        }
      ],
      "val_loss": 0.47172407309214276,
      "val_accuracy": 0.9056551853815714,
      "train_loss": 0.3662679985165596
    },
    {
      "epoch": 23,
      "train_steps": [
        {
          "step": 22,
          "loss": 0.40870723128318787
        },
        {
          "step": 44,
          "loss": 0.3071710467338562
        },
        {
          "step": 66,
          "loss": 0.352993905544281
        },
        {
          "step": 88,
          "loss": 0.32951247692108154
        },
        {
          "step": 110,
          "loss": 0.2914329171180725
        },
        {
          "step": 132,
          "loss": 0.27878260612487793
        },
        {
          "step": 154,
          "loss": 0.35865914821624756
        },
        {
          "step": 176,
          "loss": 0.3773694932460785
        },
        {
          "step": 198,
          "loss": 0.3437485694885254
        },
        {
          "step": 220,
          "loss": 0.3702812194824219
        }
      ],
      "val_loss": 0.4840055250873168,
      "val_accuracy": 0.9031988949825367,
      "train_loss": 0.3577404650774869
    },
    {
      "epoch": 24,
      "train_steps": [
        {
          "step": 22,
          "loss": 0.36789536476135254
        },
        {
          "step": 44,
          "loss": 0.36386579275131226
        },
        {
          "step": 66,
          "loss": 0.3670750558376312
        },
        {
          "step": 88,
          "loss": 0.40229862928390503
        },
        {
          "step": 110,
          "loss": 0.310696005821228
        },
        {
          "step": 132,
          "loss": 0.3680434226989746
        },
        {
          "step": 154,
          "loss": 0.2679310441017151
        },
        {
          "step": 176,
          "loss": 0.29650938510894775
        },
        {
          "step": 198,
          "loss": 0.38059866428375244
        },
        {
          "step": 220,
          "loss": 0.3954261243343353
        }
      ],
      "val_loss": 0.4839226131637891,
      "val_accuracy": 0.9032154773672422,
      "train_loss": 0.3502072689208117
    },
    {
      "epoch": 25,
      "train_steps": [
        {
          "step": 22,
          "loss": 0.3067481219768524
        },
        {
          "step": 44,
          "loss": 0.36074504256248474
        },
        {
          "step": 66,
          "loss": 0.2532600164413452
        },
        {
          "step": 88,
          "loss": 0.3957386016845703
        },
        {
          "step": 110,
          "loss": 0.27788591384887695
        },
        {
          "step": 132,
          "loss": 0.2920714318752289
        },
        {
          "step": 154,
          "loss": 0.31260156631469727
        },
        {
          "step": 176,
          "loss": 0.36819201707839966
        },
        {
          "step": 198,
          "loss": 0.3749060034751892
        },
        {
          "step": 220,
          "loss": 0.4092673659324646
        }
      ],
      "val_loss": 0.4930871569861968,
      "val_accuracy": 0.9013825686027607,
      "train_loss": 0.3499459564685822
    },
    {
      "epoch": 26,
      "train_steps": [
        {
          "step": 22,
          "loss": 0.31928780674934387
        },
        {
          "step": 44,
          "loss": 0.3469284772872925
        },
        {
          "step": 66,
          "loss": 0.27302825450897217
        },
        {
          "step": 88,
          "loss": 0.4619237780570984
        },
        {
          "step": 110,
          "loss": 0.28558647632598877
        },
        {
          "step": 132,
          "loss": 0.4241544008255005
        },
        {
          "step": 154,
          "loss": 0.27874958515167236
        },
        {
          "step": 176,
          "loss": 0.3045995831489563
        },
        {
          "step": 198,
          "loss": 0.3858320116996765
        },
        {
          "step": 220,
          "loss": 0.3689967691898346
        }
      ],
      "val_loss": 0.49736561502019566,
      "val_accuracy": 0.9005268769959609,
      "train_loss": 0.33845518150112847
    },
    {
      "epoch": 27,
      "train_steps": [
        {
          "step": 22,
          "loss": 0.4220963418483734
        },
        {
          "step": 44,
          "loss": 0.35584697127342224
        },
        {
          "step": 66,
          "loss": 0.33398860692977905
        },
        {
          "step": 88,
          "loss": 0.3035680651664734
        },
        {
          "step": 110,
          "loss": 0.339164674282074
        },
        {
          "step": 132,
          "loss": 0.3756016194820404
        },
        {
          "step": 154,
          "loss": 0.32786625623703003
        },
        {
          "step": 176,
          "loss": 0.28993672132492065
        },
        {
          "step": 198,
          "loss": 0.36238574981689453
        },
        {
          "step": 220,
          "loss": 0.31770655512809753
        }
      ],
      "val_loss": 0.49142200872302055,
      "val_accuracy": 0.9017155982553959,
      "train_loss": 0.3256166634234515
    },
    {
      "epoch": 28,
      "train_steps": [
        {
          "step": 22,
          "loss": 0.31212756037712097
        },
        {
          "step": 44,
          "loss": 0.30643031001091003
        },
        {
          "step": 66,
          "loss": 0.3648798167705536
        },
        {
          "step": 88,
          "loss": 0.26200494170188904
        },
        {
          "step": 110,
          "loss": 0.3184813857078552
        },
        {
          "step": 132,
          "loss": 0.33132511377334595
        },
        {
          "step": 154,
          "loss": 0.3055897355079651
        },
        {
          "step": 176,
          "loss": 0.41525253653526306
        },
        {
          "step": 198,
          "loss": 0.25300824642181396
        },
        {
          "step": 220,
          "loss": 0.22944335639476776
        }
      ],
      "val_loss": 0.49087681000431377,
      "val_accuracy": 0.9018246379991373,
      "train_loss": 0.3215891200710427
    },
    {
      "epoch": 29,
      "train_steps": [
        {
          "step": 22,
          "loss": 0.35694417357444763
        },
        {
          "step": 44,
          "loss": 0.34497857093811035
        },
        {
          "step": 66,
          "loss": 0.2580481171607971
        },
        {
          "step": 88,
          "loss": 0.2256135642528534
        },
        {
          "step": 110,
          "loss": 0.2712953984737396
        },
        {
          "step": 132,
          "loss": 0.31739184260368347
        },
        {
          "step": 154,
          "loss": 0.4155486226081848
        },
        {
          "step": 176,
          "loss": 0.2902076244354248
        },
        {
          "step": 198,
          "loss": 0.4427477717399597
        },
        {
          "step": 220,
          "loss": 0.5049108862876892
        }
      ],
      "val_loss": 0.5020456916342179,
      "val_accuracy": 0.8995908616731564,
      "train_loss": 0.32014355632391844
    },
    {
      "epoch": 30,
      "train_steps": [
        {
          "step": 22,
          "loss": 0.34033358097076416
        },
        {
          "step": 44,
          "loss": 0.2800901532173157
        },
        {
          "step": 66,
          "loss": 0.3548070192337036
        },
        {
          "step": 88,
          "loss": 0.3242201507091522
        },
        {
          "step": 110,
          "loss": 0.2237718552350998
        },
        {
          "step": 132,
          "loss": 0.2478070706129074
        },
        {
          "step": 154,
          "loss": 0.3260243535041809
        },
        {
          "step": 176,
          "loss": 0.26418209075927734
        },
        {
          "step": 198,
          "loss": 0.3422776460647583
        },
        {
          "step": 220,
          "loss": 0.17787373065948486
        }
      ],
      "val_loss": 0.49462627929945785,
      "val_accuracy": 0.9010747441401085,
      "train_loss": 0.3108517221429131
    },
    {
      "epoch": 31,
      "train_steps": [
        {
          "step": 22,
          "loss": 0.3112930357456207
        },
        {
          "step": 44,
          "loss": 0.2263280749320984
        },
        {
          "step": 66,
          "loss": 0.3277686834335327
        },
        {
          "step": 88,
          "loss": 0.3241031765937805
        },
        {
          "step": 110,
          "loss": 0.23731712996959686
        },
        {
          "step": 132,
          "loss": 0.4719263017177582
        },
        {
          "step": 154,
          "loss": 0.4263361096382141
        },
        {
          "step": 176,
          "loss": 0.33642274141311646
        },
        {
          "step": 198,
          "loss": 0.2761707901954651
        },
        {
          "step": 220,
          "loss": 0.2616989314556122
        }
      ],
      "val_loss": 0.48516798578202724,
      "val_accuracy": 0.9029664028435945,
      "train_loss": 0.30592514235864987
    },
    {
      "epoch": 32,
      "train_steps": [
        {
          "step": 22,
          "loss": 0.3641107976436615
        },
        {
          "step": 44,
          "loss": 0.2298567295074463
        },
        {
          "step": 66,
          "loss": 0.3644663989543915
        },
        {
          "step": 88,
          "loss": 0.36670681834220886
        },
        {
          "step": 110,
          "loss": 0.292758047580719
        },
        {
          "step": 132,
          "loss": 0.3525838851928711
        },
        {
          "step": 154,
          "loss": 0.36769843101501465
        },
        {
          "step": 176,
          "loss": 0.3345944881439209
        },
        {
          "step": 198,
          "loss": 0.38878822326660156
        },
        {
          "step": 220,
          "loss": 0.19391760230064392
        }
      ],
      "val_loss": 0.5041840535899004,
      "val_accuracy": 0.8991631892820199,
      "train_loss": 0.30557462349534037
    },
    {
      "epoch": 33,
      "train_steps": [
        {
          "step": 22,
          "loss": 0.30091795325279236
        },
        {
          "step": 44,
          "loss": 0.27880293130874634
        },
        {
          "step": 66,
          "loss": 0.21402490139007568
        },
        {
          "step": 88,
          "loss": 0.25607937574386597
        },
        {
          "step": 110,
          "loss": 0.24151389300823212
        },
        {
          "step": 132,
          "loss": 0.40106603503227234
        },
        {
          "step": 154,
          "loss": 0.3703237473964691
        },
        {
          "step": 176,
          "loss": 0.29573020339012146
        },
        {
          "step": 198,
          "loss": 0.3591312766075134
        },
        {
          "step": 220,
          "loss": 0.3706810176372528
        }
      ],
      "val_loss": 0.48056081123650074,
      "val_accuracy": 0.9038878377526999,
      "train_loss": 0.2989653460004113
    },
    {
      "epoch": 34,
      "train_steps": [
        {
          "step": 22,
          "loss": 0.2844381332397461
        },
        {
          "step": 44,
          "loss": 0.2562991976737976
        },
        {
          "step": 66,
          "loss": 0.30040067434310913
        },
        {
          "step": 88,
          "loss": 0.2625560164451599
        },
        {
          "step": 110,
          "loss": 0.3522227704524994
        },
        {
          "step": 132,
          "loss": 0.3548373878002167
        },
        {
          "step": 154,
          "loss": 0.32030004262924194
        },
        {
          "step": 176,
          "loss": 0.39041733741760254
        },
        {
          "step": 198,
          "loss": 0.3602368235588074
        },
        {
          "step": 220,
          "loss": 0.28455373644828796
        }
      ],
      "val_loss": 0.48480861199398834,
      "val_accuracy": 0.9030382776012024,
      "train_loss": 0.2952200854366476
    },
    {
      "epoch": 35,
      "train_steps": [
        {
          "step": 22,
          "loss": 0.2670080065727234
        },
        {
          "step": 44,
          "loss": 0.3354054391384125
        },
        {
          "step": 66,
          "loss": 0.23927676677703857
        },
        {
          "step": 88,
          "loss": 0.19723543524742126
        },
        {
          "step": 110,
          "loss": 0.24244330823421478
        },
        {
          "step": 132,
          "loss": 0.2876613140106201
        },
        {
          "step": 154,
          "loss": 0.38243526220321655
        },
        {
          "step": 176,
          "loss": 0.24878644943237305
        },
        {
          "step": 198,
          "loss": 0.2859944701194763
        },
        {
          "step": 220,
          "loss": 0.39557933807373047
        }
      ],
      "val_loss": 0.4855624201397101,
      "val_accuracy": 0.902887515972058,
      "train_loss": 0.2959507601504976
    },
    {
      "epoch": 36,
      "train_steps": [
        {
          "step": 22,
          "loss": 0.22161567211151123
        },
        {
          "step": 44,
          "loss": 0.28090816736221313
        },
        {
          "step": 66,
          "loss": 0.3298652768135071
        },
        {
          "step": 88,
          "loss": 0.35889002680778503
        },
        {
          "step": 110,
          "loss": 0.3004453778266907
        },
        {
          "step": 132,
          "loss": 0.2494010627269745
        },
        {
          "step": 154,
          "loss": 0.36258792877197266
        },
        {
          "step": 176,
          "loss": 0.26308274269104004
        },
        {
          "step": 198,
          "loss": 0.3362700343132019
        },
        {
          "step": 220,
          "loss": 0.3581990897655487
        }
      ],
      "val_loss": 0.5120880727966627,
      "val_accuracy": 0.8975823854406675,
      "train_loss": 0.2923543124036355
    },
    {
      "epoch": 37,
      "train_steps": [
        {
          "step": 22,
          "loss": 0.27857932448387146
        },
        {
          "step": 44,
          "loss": 0.24359242618083954
        },
        {
          "step": 66,
          "loss": 0.2166292667388916
        },
        {
          "step": 88,
          "loss": 0.23987935483455658
        },
        {
          "step": 110,
          "loss": 0.28582778573036194
        },
        {
          "step": 132,
          "loss": 0.4547748565673828
        },
        {
          "step": 154,
          "loss": 0.31213629245758057
        },
        {
          "step": 176,
          "loss": 0.23693013191223145
        },
        {
          "step": 198,
          "loss": 0.28896135091781616
        },
        {
          "step": 220,
          "loss": 0.3351651728153229
        }
      ],
      "val_loss": 0.5054225244869789,
      "val_accuracy": 0.8989154951026043,
      "train_loss": 0.2824870843778957
    },
    {
      "epoch": 38,
      "train_steps": [
        {
          "step": 22,
          "loss": 0.2594558000564575
        },
        {
          "step": 44,
          "loss": 0.20591089129447937
        },
        {
          "step": 66,
          "loss": 0.23525938391685486
        },
        {
          "step": 88,
          "loss": 0.2586851716041565
        },
        {
          "step": 110,
          "loss": 0.2736673057079315
        },
        {
          "step": 132,
          "loss": 0.2758671045303345
        },
        {
          "step": 154,
          "loss": 0.3753422200679779
        },
        {
          "step": 176,
          "loss": 0.21856817603111267
        },
        {
          "step": 198,
          "loss": 0.2905063033103943
        },
        {
          "step": 220,
          "loss": 0.3020400404930115
        }
      ],
      "val_loss": 0.4989179490755002,
      "val_accuracy": 0.9002164101849,
      "train_loss": 0.2852239757098935
    },
    {
      "epoch": 39,
      "train_steps": [
        {
          "step": 22,
          "loss": 0.22457727789878845
        },
        {
          "step": 44,
          "loss": 0.26969820261001587
        },
        {
          "step": 66,
          "loss": 0.38098353147506714
        },
        {
          "step": 88,
          "loss": 0.3186921775341034
        },
        {
          "step": 110,
          "loss": 0.2521624267101288
        },
        {
          "step": 132,
          "loss": 0.2288789451122284
        },
        {
          "step": 154,
          "loss": 0.20802545547485352
        },
        {
          "step": 176,
          "loss": 0.3560640811920166
        },
        {
          "step": 198,
          "loss": 0.330658495426178
        },
        {
          "step": 220,
          "loss": 0.20715385675430298
        }
      ],
      "val_loss": 0.4835527042547862,
      "val_accuracy": 0.9032894591490428,
      "train_loss": 0.2813176772133871
    },
    {
      "epoch": 40,
      "train_steps": [
        {
          "step": 22,
          "loss": 0.1989911049604416
        },
        {
          "step": 44,
          "loss": 0.2733980119228363
        },
        {
          "step": 66,
          "loss": 0.24958370625972748
        },
        {
          "step": 88,
          "loss": 0.1999141424894333
        },
        {
          "step": 110,
          "loss": 0.26549971103668213
        },
        {
          "step": 132,
          "loss": 0.34169912338256836
        },
        {
          "step": 154,
          "loss": 0.21480193734169006
        },
        {
          "step": 176,
          "loss": 0.26490530371665955
        },
        {
          "step": 198,
          "loss": 0.24785837531089783
        },
        {
          "step": 220,
          "loss": 0.23007875680923462
        }
      ],
      "val_loss": 0.4902639544258515,
      "val_accuracy": 0.9019472091148297,
      "train_loss": 0.277834615720944
    }
  ],
  "audio_feature": "spectrogram",
  "fusion_type": "attention"
}