{
  "model_name": "distilbert-base-uncased",
  "dataset": "IEMOCAP_Filtered",
  "experiment_type": "multimodal",
  "epochs": 40,
  "batch_size": 32,
  "train_samples": 5870,
  "val_samples": 1258,
  "test_samples": 1259,
  "epoch_logs": [
    {
      "epoch": 1,
      "train_steps": [
        {
          "step": 18,
          "loss": 8.397611618041992
        },
        {
          "step": 36,
          "loss": 6.38062858581543
        },
        {
          "step": 54,
          "loss": 5.616009712219238
        },
        {
          "step": 72,
          "loss": 5.08398962020874
        },
        {
          "step": 90,
          "loss": 4.5804033279418945
        },
        {
          "step": 108,
          "loss": 3.7180469036102295
        },
        {
          "step": 126,
          "loss": 2.907440185546875
        },
        {
          "step": 144,
          "loss": 2.977726936340332
        },
        {
          "step": 162,
          "loss": 1.7834419012069702
        },
        {
          "step": 180,
          "loss": 1.7931406497955322
        }
      ],
      "val_loss": 1.4686651289463044,
      "val_accuracy": 0.7062669742107391,
      "train_loss": 4.720099074037178
    },
    {
      "epoch": 2,
      "train_steps": [
        {
          "step": 18,
          "loss": 1.5608630180358887
        },
        {
          "step": 36,
          "loss": 1.3793020248413086
        },
        {
          "step": 54,
          "loss": 1.2323310375213623
        },
        {
          "step": 72,
          "loss": 0.8731950521469116
        },
        {
          "step": 90,
          "loss": 0.9209591746330261
        },
        {
          "step": 108,
          "loss": 0.9840954542160034
        },
        {
          "step": 126,
          "loss": 0.9357436895370483
        },
        {
          "step": 144,
          "loss": 0.7546629309654236
        },
        {
          "step": 162,
          "loss": 1.1043996810913086
        },
        {
          "step": 180,
          "loss": 1.029222011566162
        }
      ],
      "val_loss": 0.6310574457049369,
      "val_accuracy": 0.8737885108590127,
      "train_loss": 1.188199352958928
    },
    {
      "epoch": 3,
      "train_steps": [
        {
          "step": 18,
          "loss": 1.0657076835632324
        },
        {
          "step": 36,
          "loss": 1.1223982572555542
        },
        {
          "step": 54,
          "loss": 1.197668433189392
        },
        {
          "step": 72,
          "loss": 1.1711249351501465
        },
        {
          "step": 90,
          "loss": 0.811212420463562
        },
        {
          "step": 108,
          "loss": 0.9549266695976257
        },
        {
          "step": 126,
          "loss": 0.8936944007873535
        },
        {
          "step": 144,
          "loss": 1.0700998306274414
        },
        {
          "step": 162,
          "loss": 1.1431465148925781
        },
        {
          "step": 180,
          "loss": 0.8321229815483093
        }
      ],
      "val_loss": 0.591093773394823,
      "val_accuracy": 0.8817812453210354,
      "train_loss": 0.9709100477073503
    },
    {
      "epoch": 4,
      "train_steps": [
        {
          "step": 18,
          "loss": 1.0304605960845947
        },
        {
          "step": 36,
          "loss": 1.045796275138855
        },
        {
          "step": 54,
          "loss": 0.802605152130127
        },
        {
          "step": 72,
          "loss": 1.0211635828018188
        },
        {
          "step": 90,
          "loss": 0.9283086657524109
        },
        {
          "step": 108,
          "loss": 0.6554612517356873
        },
        {
          "step": 126,
          "loss": 0.8663716316223145
        },
        {
          "step": 144,
          "loss": 0.9528073072433472
        },
        {
          "step": 162,
          "loss": 0.7152395248413086
        },
        {
          "step": 180,
          "loss": 0.9042338132858276
        }
      ],
      "val_loss": 0.5437329031527043,
      "val_accuracy": 0.8912534193694591,
      "train_loss": 0.9053009071427843
    },
    {
      "epoch": 5,
      "train_steps": [
        {
          "step": 18,
          "loss": 0.8054566383361816
        },
        {
          "step": 36,
          "loss": 0.8831993937492371
        },
        {
          "step": 54,
          "loss": 0.8332914710044861
        },
        {
          "step": 72,
          "loss": 0.8443028330802917
        },
        {
          "step": 90,
          "loss": 0.7049404978752136
        },
        {
          "step": 108,
          "loss": 0.8441524505615234
        },
        {
          "step": 126,
          "loss": 0.9395381808280945
        },
        {
          "step": 144,
          "loss": 0.7740696668624878
        },
        {
          "step": 162,
          "loss": 1.0549293756484985
        },
        {
          "step": 180,
          "loss": 0.6980106234550476
        }
      ],
      "val_loss": 0.5142608091235161,
      "val_accuracy": 0.8971478381752968,
      "train_loss": 0.8243788296113843
    },
    {
      "epoch": 6,
      "train_steps": [
        {
          "step": 18,
          "loss": 0.614963173866272
        },
        {
          "step": 36,
          "loss": 0.7438832521438599
        },
        {
          "step": 54,
          "loss": 0.7015194892883301
        },
        {
          "step": 72,
          "loss": 0.7500540614128113
        },
        {
          "step": 90,
          "loss": 0.6776983737945557
        },
        {
          "step": 108,
          "loss": 0.9542810916900635
        },
        {
          "step": 126,
          "loss": 0.6536108255386353
        },
        {
          "step": 144,
          "loss": 0.8098697066307068
        },
        {
          "step": 162,
          "loss": 0.6116644144058228
        },
        {
          "step": 180,
          "loss": 0.6504205465316772
        }
      ],
      "val_loss": 0.46880247369408606,
      "val_accuracy": 0.9062395052611828,
      "train_loss": 0.741438953610866
    },
    {
      "epoch": 7,
      "train_steps": [
        {
          "step": 18,
          "loss": 0.6378610134124756
        },
        {
          "step": 36,
          "loss": 0.7995654940605164
        },
        {
          "step": 54,
          "loss": 0.5906545519828796
        },
        {
          "step": 72,
          "loss": 0.7792279720306396
        },
        {
          "step": 90,
          "loss": 0.9043740630149841
        },
        {
          "step": 108,
          "loss": 0.7911378741264343
        },
        {
          "step": 126,
          "loss": 0.9088002443313599
        },
        {
          "step": 144,
          "loss": 0.6678916811943054
        },
        {
          "step": 162,
          "loss": 0.7494623064994812
        },
        {
          "step": 180,
          "loss": 0.5976976156234741
        }
      ],
      "val_loss": 0.466140828281641,
      "val_accuracy": 0.9067718343436718,
      "train_loss": 0.6863206885755062
    },
    {
      "epoch": 8,
      "train_steps": [
        {
          "step": 18,
          "loss": 0.6848058700561523
        },
        {
          "step": 36,
          "loss": 0.6568536162376404
        },
        {
          "step": 54,
          "loss": 0.9679209589958191
        },
        {
          "step": 72,
          "loss": 0.6197590231895447
        },
        {
          "step": 90,
          "loss": 0.6052030324935913
        },
        {
          "step": 108,
          "loss": 0.587878942489624
        },
        {
          "step": 126,
          "loss": 0.6178985834121704
        },
        {
          "step": 144,
          "loss": 0.5488390922546387
        },
        {
          "step": 162,
          "loss": 0.4888290762901306
        },
        {
          "step": 180,
          "loss": 0.6770970225334167
        }
      ],
      "val_loss": 0.44962494522333146,
      "val_accuracy": 0.9100750109553337,
      "train_loss": 0.6526557367456995
    },
    {
      "epoch": 9,
      "train_steps": [
        {
          "step": 18,
          "loss": 0.547236442565918
        },
        {
          "step": 36,
          "loss": 0.5819761157035828
        },
        {
          "step": 54,
          "loss": 0.3573176860809326
        },
        {
          "step": 72,
          "loss": 0.5623859167098999
        },
        {
          "step": 90,
          "loss": 0.6809616088867188
        },
        {
          "step": 108,
          "loss": 0.48149213194847107
        },
        {
          "step": 126,
          "loss": 0.7271530032157898
        },
        {
          "step": 144,
          "loss": 0.7428881525993347
        },
        {
          "step": 162,
          "loss": 0.8505784273147583
        },
        {
          "step": 180,
          "loss": 0.6903087496757507
        }
      ],
      "val_loss": 0.4555589981377125,
      "val_accuracy": 0.9088882003724575,
      "train_loss": 0.611005184929008
    },
    {
      "epoch": 10,
      "train_steps": [
        {
          "step": 18,
          "loss": 0.4615217447280884
        },
        {
          "step": 36,
          "loss": 0.5647112131118774
        },
        {
          "step": 54,
          "loss": 0.654717206954956
        },
        {
          "step": 72,
          "loss": 0.5856230854988098
        },
        {
          "step": 90,
          "loss": 0.7224869132041931
        },
        {
          "step": 108,
          "loss": 0.5731309652328491
        },
        {
          "step": 126,
          "loss": 0.5658056735992432
        },
        {
          "step": 144,
          "loss": 0.556658148765564
        },
        {
          "step": 162,
          "loss": 0.5090598464012146
        },
        {
          "step": 180,
          "loss": 0.5194190740585327
        }
      ],
      "val_loss": 0.4658479690551758,
      "val_accuracy": 0.9068304061889648,
      "train_loss": 0.5915097341589306
    },
    {
      "epoch": 11,
      "train_steps": [
        {
          "step": 18,
          "loss": 0.6518332958221436
        },
        {
          "step": 36,
          "loss": 0.7186335325241089
        },
        {
          "step": 54,
          "loss": 0.5794579982757568
        },
        {
          "step": 72,
          "loss": 0.4223577380180359
        },
        {
          "step": 90,
          "loss": 0.5940097570419312
        },
        {
          "step": 108,
          "loss": 0.5827080011367798
        },
        {
          "step": 126,
          "loss": 0.5597012042999268
        },
        {
          "step": 144,
          "loss": 0.5471932291984558
        },
        {
          "step": 162,
          "loss": 0.6500223875045776
        },
        {
          "step": 180,
          "loss": 0.5667693614959717
        }
      ],
      "val_loss": 0.4677229605615139,
      "val_accuracy": 0.9064554078876972,
      "train_loss": 0.5605078245634618
    },
    {
      "epoch": 12,
      "train_steps": [
        {
          "step": 18,
          "loss": 0.6124235987663269
        },
        {
          "step": 36,
          "loss": 0.520697832107544
        },
        {
          "step": 54,
          "loss": 0.38202032446861267
        },
        {
          "step": 72,
          "loss": 0.4013959765434265
        },
        {
          "step": 90,
          "loss": 0.4893381595611572
        },
        {
          "step": 108,
          "loss": 0.44273561239242554
        },
        {
          "step": 126,
          "loss": 0.4459020495414734
        },
        {
          "step": 144,
          "loss": 0.4876480996608734
        },
        {
          "step": 162,
          "loss": 0.4661186635494232
        },
        {
          "step": 180,
          "loss": 0.34813839197158813
        }
      ],
      "val_loss": 0.46394920349121094,
      "val_accuracy": 0.9072101593017579,
      "train_loss": 0.5253106133769387
    },
    {
      "epoch": 13,
      "train_steps": [
        {
          "step": 18,
          "loss": 0.409975528717041
        },
        {
          "step": 36,
          "loss": 0.3907654881477356
        },
        {
          "step": 54,
          "loss": 0.6952608823776245
        },
        {
          "step": 72,
          "loss": 0.5231012105941772
        },
        {
          "step": 90,
          "loss": 0.6640350818634033
        },
        {
          "step": 108,
          "loss": 0.49369311332702637
        },
        {
          "step": 126,
          "loss": 0.4374268054962158
        },
        {
          "step": 144,
          "loss": 0.529593288898468
        },
        {
          "step": 162,
          "loss": 0.49971330165863037
        },
        {
          "step": 180,
          "loss": 0.610550582408905
        }
      ],
      "val_loss": 0.4510844454169273,
      "val_accuracy": 0.9097831109166146,
      "train_loss": 0.5093679800629616
    },
    {
      "epoch": 14,
      "train_steps": [
        {
          "step": 18,
          "loss": 0.481940358877182
        },
        {
          "step": 36,
          "loss": 0.5444750785827637
        },
        {
          "step": 54,
          "loss": 0.3196204602718353
        },
        {
          "step": 72,
          "loss": 0.42596107721328735
        },
        {
          "step": 90,
          "loss": 0.4031323194503784
        },
        {
          "step": 108,
          "loss": 0.3858770728111267
        },
        {
          "step": 126,
          "loss": 0.5450195074081421
        },
        {
          "step": 144,
          "loss": 0.40761512517929077
        },
        {
          "step": 162,
          "loss": 0.378121018409729
        },
        {
          "step": 180,
          "loss": 0.49902939796447754
        }
      ],
      "val_loss": 0.4640043698251247,
      "val_accuracy": 0.9071991260349751,
      "train_loss": 0.4795854898250621
    },
    {
      "epoch": 15,
      "train_steps": [
        {
          "step": 18,
          "loss": 0.4709402024745941
        },
        {
          "step": 36,
          "loss": 0.6347190737724304
        },
        {
          "step": 54,
          "loss": 0.4298529028892517
        },
        {
          "step": 72,
          "loss": 0.4607686698436737
        },
        {
          "step": 90,
          "loss": 0.44353827834129333
        },
        {
          "step": 108,
          "loss": 0.3895235061645508
        },
        {
          "step": 126,
          "loss": 0.5427955389022827
        },
        {
          "step": 144,
          "loss": 0.44690293073654175
        },
        {
          "step": 162,
          "loss": 0.4124424457550049
        },
        {
          "step": 180,
          "loss": 0.4713497757911682
        }
      ],
      "val_loss": 0.469613815844059,
      "val_accuracy": 0.9060772368311882,
      "train_loss": 0.46606825162535126
    },
    {
      "epoch": 16,
      "train_steps": [
        {
          "step": 18,
          "loss": 0.42986297607421875
        },
        {
          "step": 36,
          "loss": 0.4143712520599365
        },
        {
          "step": 54,
          "loss": 0.5841604471206665
        },
        {
          "step": 72,
          "loss": 0.45478829741477966
        },
        {
          "step": 90,
          "loss": 0.4158799648284912
        },
        {
          "step": 108,
          "loss": 0.4039505422115326
        },
        {
          "step": 126,
          "loss": 0.5146946907043457
        },
        {
          "step": 144,
          "loss": 0.5224823355674744
        },
        {
          "step": 162,
          "loss": 0.5206418037414551
        },
        {
          "step": 180,
          "loss": 0.34968632459640503
        }
      ],
      "val_loss": 0.4639230243861675,
      "val_accuracy": 0.9072153951227665,
      "train_loss": 0.45305459266123566
    },
    {
      "epoch": 17,
      "train_steps": [
        {
          "step": 18,
          "loss": 0.38981592655181885
        },
        {
          "step": 36,
          "loss": 0.4286388158798218
        },
        {
          "step": 54,
          "loss": 0.33146268129348755
        },
        {
          "step": 72,
          "loss": 0.35102832317352295
        },
        {
          "step": 90,
          "loss": 0.4721412658691406
        },
        {
          "step": 108,
          "loss": 0.4006507396697998
        },
        {
          "step": 126,
          "loss": 0.4211277961730957
        },
        {
          "step": 144,
          "loss": 0.4241587519645691
        },
        {
          "step": 162,
          "loss": 0.2878463864326477
        },
        {
          "step": 180,
          "loss": 0.3106445074081421
        }
      ],
      "val_loss": 0.48636740148067475,
      "val_accuracy": 0.9027265197038651,
      "train_loss": 0.42669926648554596
    },
    {
      "epoch": 18,
      "train_steps": [
        {
          "step": 18,
          "loss": 0.3579563796520233
        },
        {
          "step": 36,
          "loss": 0.33147284388542175
        },
        {
          "step": 54,
          "loss": 0.3788468837738037
        },
        {
          "step": 72,
          "loss": 0.4374625086784363
        },
        {
          "step": 90,
          "loss": 0.5679828524589539
        },
        {
          "step": 108,
          "loss": 0.4526546895503998
        },
        {
          "step": 126,
          "loss": 0.47424718737602234
        },
        {
          "step": 144,
          "loss": 0.36722156405448914
        },
        {
          "step": 162,
          "loss": 0.4902157187461853
        },
        {
          "step": 180,
          "loss": 0.40081077814102173
        }
      ],
      "val_loss": 0.467441526055336,
      "val_accuracy": 0.9065116947889328,
      "train_loss": 0.40942892043486884
    },
    {
      "epoch": 19,
      "train_steps": [
        {
          "step": 18,
          "loss": 0.35379356145858765
        },
        {
          "step": 36,
          "loss": 0.42890021204948425
        },
        {
          "step": 54,
          "loss": 0.23895536363124847
        },
        {
          "step": 72,
          "loss": 0.36571356654167175
        },
        {
          "step": 90,
          "loss": 0.4955556392669678
        },
        {
          "step": 108,
          "loss": 0.43220055103302
        },
        {
          "step": 126,
          "loss": 0.37355121970176697
        },
        {
          "step": 144,
          "loss": 0.4994930922985077
        },
        {
          "step": 162,
          "loss": 0.4437894821166992
        },
        {
          "step": 180,
          "loss": 0.35114777088165283
        }
      ],
      "val_loss": 0.4629882998764515,
      "val_accuracy": 0.9074023400247097,
      "train_loss": 0.4007954152867846
    },
    {
      "epoch": 20,
      "train_steps": [
        {
          "step": 18,
          "loss": 0.31693124771118164
        },
        {
          "step": 36,
          "loss": 0.36543160676956177
        },
        {
          "step": 54,
          "loss": 0.33694013953208923
        },
        {
          "step": 72,
          "loss": 0.35268181562423706
        },
        {
          "step": 90,
          "loss": 0.37572211027145386
        },
        {
          "step": 108,
          "loss": 0.3706836402416229
        },
        {
          "step": 126,
          "loss": 0.39886340498924255
        },
        {
          "step": 144,
          "loss": 0.488243043422699
        },
        {
          "step": 162,
          "loss": 0.36470144987106323
        },
        {
          "step": 180,
          "loss": 0.4406284689903259
        }
      ],
      "val_loss": 0.4786893866956234,
      "val_accuracy": 0.9042621226608754,
      "train_loss": 0.38726971549508366
    },
    {
      "epoch": 21,
      "train_steps": [
        {
          "step": 18,
          "loss": 0.2751278579235077
        },
        {
          "step": 36,
          "loss": 0.41942542791366577
        },
        {
          "step": 54,
          "loss": 0.2422698736190796
        },
        {
          "step": 72,
          "loss": 0.43441838026046753
        },
        {
          "step": 90,
          "loss": 0.4349184036254883
        },
        {
          "step": 108,
          "loss": 0.335543155670166
        },
        {
          "step": 126,
          "loss": 0.4307636618614197
        },
        {
          "step": 144,
          "loss": 0.4615752100944519
        },
        {
          "step": 162,
          "loss": 0.3607153296470642
        },
        {
          "step": 180,
          "loss": 0.49266108870506287
        }
      ],
      "val_loss": 0.4767363786697388,
      "val_accuracy": 0.9046527242660523,
      "train_loss": 0.381764595437309
    },
    {
      "epoch": 22,
      "train_steps": [
        {
          "step": 18,
          "loss": 0.317182719707489
        },
        {
          "step": 36,
          "loss": 0.369785875082016
        },
        {
          "step": 54,
          "loss": 0.32932308316230774
        },
        {
          "step": 72,
          "loss": 0.44427844882011414
        },
        {
          "step": 90,
          "loss": 0.31099018454551697
        },
        {
          "step": 108,
          "loss": 0.38958901166915894
        },
        {
          "step": 126,
          "loss": 0.3714866042137146
        },
        {
          "step": 144,
          "loss": 0.37283939123153687
        },
        {
          "step": 162,
          "loss": 0.4931662976741791
        },
        {
          "step": 180,
          "loss": 0.33962762355804443
        }
      ],
      "val_loss": 0.4882983736693859,
      "val_accuracy": 0.9023403252661228,
      "train_loss": 0.366513654589653
    },
    {
      "epoch": 23,
      "train_steps": [
        {
          "step": 18,
          "loss": 0.3689737915992737
        },
        {
          "step": 36,
          "loss": 0.2673919200897217
        },
        {
          "step": 54,
          "loss": 0.3105621933937073
        },
        {
          "step": 72,
          "loss": 0.32831546664237976
        },
        {
          "step": 90,
          "loss": 0.32095202803611755
        },
        {
          "step": 108,
          "loss": 0.3896133303642273
        },
        {
          "step": 126,
          "loss": 0.32382574677467346
        },
        {
          "step": 144,
          "loss": 0.3442420959472656
        },
        {
          "step": 162,
          "loss": 0.3262676000595093
        },
        {
          "step": 180,
          "loss": 0.33292752504348755
        }
      ],
      "val_loss": 0.4704574219882488,
      "val_accuracy": 0.9059085156023502,
      "train_loss": 0.35457974826188193
    },
    {
      "epoch": 24,
      "train_steps": [
        {
          "step": 18,
          "loss": 0.3322208523750305
        },
        {
          "step": 36,
          "loss": 0.29649001359939575
        },
        {
          "step": 54,
          "loss": 0.4217475354671478
        },
        {
          "step": 72,
          "loss": 0.27093538641929626
        },
        {
          "step": 90,
          "loss": 0.39696282148361206
        },
        {
          "step": 108,
          "loss": 0.4077557921409607
        },
        {
          "step": 126,
          "loss": 0.25668346881866455
        },
        {
          "step": 144,
          "loss": 0.296207994222641
        },
        {
          "step": 162,
          "loss": 0.3895663619041443
        },
        {
          "step": 180,
          "loss": 0.40866440534591675
        }
      ],
      "val_loss": 0.4818672776222229,
      "val_accuracy": 0.9036265444755555,
      "train_loss": 0.3548473073574512
    },
    {
      "epoch": 25,
      "train_steps": [
        {
          "step": 18,
          "loss": 0.287062406539917
        },
        {
          "step": 36,
          "loss": 0.3911256194114685
        },
        {
          "step": 54,
          "loss": 0.37716028094291687
        },
        {
          "step": 72,
          "loss": 0.3280628025531769
        },
        {
          "step": 90,
          "loss": 0.2803082764148712
        },
        {
          "step": 108,
          "loss": 0.2796058654785156
        },
        {
          "step": 126,
          "loss": 0.3349509835243225
        },
        {
          "step": 144,
          "loss": 0.3742968440055847
        },
        {
          "step": 162,
          "loss": 0.33269503712654114
        },
        {
          "step": 180,
          "loss": 0.40542006492614746
        }
      ],
      "val_loss": 0.4858258716762066,
      "val_accuracy": 0.9028348256647587,
      "train_loss": 0.33931404627535655
    },
    {
      "epoch": 26,
      "train_steps": [
        {
          "step": 18,
          "loss": 0.41749876737594604
        },
        {
          "step": 36,
          "loss": 0.47175416350364685
        },
        {
          "step": 54,
          "loss": 0.35790762305259705
        },
        {
          "step": 72,
          "loss": 0.31414663791656494
        },
        {
          "step": 90,
          "loss": 0.36452364921569824
        },
        {
          "step": 108,
          "loss": 0.3147009313106537
        },
        {
          "step": 126,
          "loss": 0.31442323327064514
        },
        {
          "step": 144,
          "loss": 0.32376164197921753
        },
        {
          "step": 162,
          "loss": 0.36063480377197266
        },
        {
          "step": 180,
          "loss": 0.3687007427215576
        }
      ],
      "val_loss": 0.47847200855612754,
      "val_accuracy": 0.9043055982887744,
      "train_loss": 0.33863991588030173
    },
    {
      "epoch": 27,
      "train_steps": [
        {
          "step": 18,
          "loss": 0.26914387941360474
        },
        {
          "step": 36,
          "loss": 0.29287952184677124
        },
        {
          "step": 54,
          "loss": 0.28681471943855286
        },
        {
          "step": 72,
          "loss": 0.34915846586227417
        },
        {
          "step": 90,
          "loss": 0.2888980805873871
        },
        {
          "step": 108,
          "loss": 0.20206575095653534
        },
        {
          "step": 126,
          "loss": 0.3555864691734314
        },
        {
          "step": 144,
          "loss": 0.30555978417396545
        },
        {
          "step": 162,
          "loss": 0.29820138216018677
        },
        {
          "step": 180,
          "loss": 0.31672191619873047
        }
      ],
      "val_loss": 0.47635249570012095,
      "val_accuracy": 0.9047295008599758,
      "train_loss": 0.32463012481837167
    },
    {
      "epoch": 28,
      "train_steps": [
        {
          "step": 18,
          "loss": 0.3957202434539795
        },
        {
          "step": 36,
          "loss": 0.4251655042171478
        },
        {
          "step": 54,
          "loss": 0.31623154878616333
        },
        {
          "step": 72,
          "loss": 0.30036887526512146
        },
        {
          "step": 90,
          "loss": 0.19095012545585632
        },
        {
          "step": 108,
          "loss": 0.2762725353240967
        },
        {
          "step": 126,
          "loss": 0.30474478006362915
        },
        {
          "step": 144,
          "loss": 0.1896546483039856
        },
        {
          "step": 162,
          "loss": 0.44983160495758057
        },
        {
          "step": 180,
          "loss": 0.42053818702697754
        }
      ],
      "val_loss": 0.4929939366877079,
      "val_accuracy": 0.9014012126624584,
      "train_loss": 0.32025210850912594
    },
    {
      "epoch": 29,
      "train_steps": [
        {
          "step": 18,
          "loss": 0.3002709448337555
        },
        {
          "step": 36,
          "loss": 0.27391791343688965
        },
        {
          "step": 54,
          "loss": 0.2861540615558624
        },
        {
          "step": 72,
          "loss": 0.3001112937927246
        },
        {
          "step": 90,
          "loss": 0.37670835852622986
        },
        {
          "step": 108,
          "loss": 0.23939482867717743
        },
        {
          "step": 126,
          "loss": 0.33889275789260864
        },
        {
          "step": 144,
          "loss": 0.2938923239707947
        },
        {
          "step": 162,
          "loss": 0.3004559278488159
        },
        {
          "step": 180,
          "loss": 0.30288076400756836
        }
      ],
      "val_loss": 0.4897576794028282,
      "val_accuracy": 0.9020484641194344,
      "train_loss": 0.31446334233750467
    },
    {
      "epoch": 30,
      "train_steps": [
        {
          "step": 18,
          "loss": 0.42970752716064453
        },
        {
          "step": 36,
          "loss": 0.45170438289642334
        },
        {
          "step": 54,
          "loss": 0.3241572380065918
        },
        {
          "step": 72,
          "loss": 0.34459349513053894
        },
        {
          "step": 90,
          "loss": 0.367459237575531
        },
        {
          "step": 108,
          "loss": 0.3171306550502777
        },
        {
          "step": 126,
          "loss": 0.370827317237854
        },
        {
          "step": 144,
          "loss": 0.29679328203201294
        },
        {
          "step": 162,
          "loss": 0.25472915172576904
        },
        {
          "step": 180,
          "loss": 0.2788842022418976
        }
      ],
      "val_loss": 0.4870449550449848,
      "val_accuracy": 0.9025910089910031,
      "train_loss": 0.31102876567646215
    },
    {
      "epoch": 31,
      "train_steps": [
        {
          "step": 18,
          "loss": 0.3133264482021332
        },
        {
          "step": 36,
          "loss": 0.25399050116539
        },
        {
          "step": 54,
          "loss": 0.3241840600967407
        },
        {
          "step": 72,
          "loss": 0.26130884885787964
        },
        {
          "step": 90,
          "loss": 0.32422658801078796
        },
        {
          "step": 108,
          "loss": 0.28435564041137695
        },
        {
          "step": 126,
          "loss": 0.3141862750053406
        },
        {
          "step": 144,
          "loss": 0.3299051523208618
        },
        {
          "step": 162,
          "loss": 0.26610997319221497
        },
        {
          "step": 180,
          "loss": 0.32269904017448425
        }
      ],
      "val_loss": 0.5104607902467251,
      "val_accuracy": 0.897907841950655,
      "train_loss": 0.29843980430260947
    },
    {
      "epoch": 32,
      "train_steps": [
        {
          "step": 18,
          "loss": 0.24838761985301971
        },
        {
          "step": 36,
          "loss": 0.3713456094264984
        },
        {
          "step": 54,
          "loss": 0.26440948247909546
        },
        {
          "step": 72,
          "loss": 0.2884049415588379
        },
        {
          "step": 90,
          "loss": 0.3118264079093933
        },
        {
          "step": 108,
          "loss": 0.26808664202690125
        },
        {
          "step": 126,
          "loss": 0.35875916481018066
        },
        {
          "step": 144,
          "loss": 0.32664117217063904
        },
        {
          "step": 162,
          "loss": 0.3001610040664673
        },
        {
          "step": 180,
          "loss": 0.28473585844039917
        }
      ],
      "val_loss": 0.5009322620928287,
      "val_accuracy": 0.8998135475814343,
      "train_loss": 0.2946245741585027
    },
    {
      "epoch": 33,
      "train_steps": [
        {
          "step": 18,
          "loss": 0.35218116641044617
        },
        {
          "step": 36,
          "loss": 0.2836379408836365
        },
        {
          "step": 54,
          "loss": 0.25443729758262634
        },
        {
          "step": 72,
          "loss": 0.378550261259079
        },
        {
          "step": 90,
          "loss": 0.3628380298614502
        },
        {
          "step": 108,
          "loss": 0.27824127674102783
        },
        {
          "step": 126,
          "loss": 0.41425496339797974
        },
        {
          "step": 144,
          "loss": 0.2836458086967468
        },
        {
          "step": 162,
          "loss": 0.2828800678253174
        },
        {
          "step": 180,
          "loss": 0.33009999990463257
        }
      ],
      "val_loss": 0.49644831717014315,
      "val_accuracy": 0.9007103365659713,
      "train_loss": 0.2979050187960915
    },
    {
      "epoch": 34,
      "train_steps": [
        {
          "step": 18,
          "loss": 0.2569442391395569
        },
        {
          "step": 36,
          "loss": 0.4150282144546509
        },
        {
          "step": 54,
          "loss": 0.33962929248809814
        },
        {
          "step": 72,
          "loss": 0.2762293815612793
        },
        {
          "step": 90,
          "loss": 0.3521828353404999
        },
        {
          "step": 108,
          "loss": 0.33012956380844116
        },
        {
          "step": 126,
          "loss": 0.2978440821170807
        },
        {
          "step": 144,
          "loss": 0.2864031195640564
        },
        {
          "step": 162,
          "loss": 0.3149762749671936
        },
        {
          "step": 180,
          "loss": 0.28638017177581787
        }
      ],
      "val_loss": 0.5159963093698025,
      "val_accuracy": 0.8968007381260396,
      "train_loss": 0.2831949722021818
    },
    {
      "epoch": 35,
      "train_steps": [
        {
          "step": 18,
          "loss": 0.33772796392440796
        },
        {
          "step": 36,
          "loss": 0.28065556287765503
        },
        {
          "step": 54,
          "loss": 0.2364320009946823
        },
        {
          "step": 72,
          "loss": 0.24160459637641907
        },
        {
          "step": 90,
          "loss": 0.3095039129257202
        },
        {
          "step": 108,
          "loss": 0.24818453192710876
        },
        {
          "step": 126,
          "loss": 0.27306029200553894
        },
        {
          "step": 144,
          "loss": 0.25616613030433655
        },
        {
          "step": 162,
          "loss": 0.2597978115081787
        },
        {
          "step": 180,
          "loss": 0.2868872284889221
        }
      ],
      "val_loss": 0.49205193519592283,
      "val_accuracy": 0.9015896129608154,
      "train_loss": 0.28558757836404053
    },
    {
      "epoch": 36,
      "train_steps": [
        {
          "step": 18,
          "loss": 0.2633242607116699
        },
        {
          "step": 36,
          "loss": 0.36100348830223083
        },
        {
          "step": 54,
          "loss": 0.2539328932762146
        },
        {
          "step": 72,
          "loss": 0.32220038771629333
        },
        {
          "step": 90,
          "loss": 0.34368273615837097
        },
        {
          "step": 108,
          "loss": 0.44604381918907166
        },
        {
          "step": 126,
          "loss": 0.23281943798065186
        },
        {
          "step": 144,
          "loss": 0.2851182818412781
        },
        {
          "step": 162,
          "loss": 0.2073194831609726
        },
        {
          "step": 180,
          "loss": 0.32904738187789917
        }
      ],
      "val_loss": 0.5045350901782513,
      "val_accuracy": 0.8990929819643497,
      "train_loss": 0.2799086288103591
    },
    {
      "epoch": 37,
      "train_steps": [
        {
          "step": 18,
          "loss": 0.19492386281490326
        },
        {
          "step": 36,
          "loss": 0.26308390498161316
        },
        {
          "step": 54,
          "loss": 0.23855333030223846
        },
        {
          "step": 72,
          "loss": 0.3025586009025574
        },
        {
          "step": 90,
          "loss": 0.24676787853240967
        },
        {
          "step": 108,
          "loss": 0.3174927234649658
        },
        {
          "step": 126,
          "loss": 0.2989528775215149
        },
        {
          "step": 144,
          "loss": 0.28083372116088867
        },
        {
          "step": 162,
          "loss": 0.2932817041873932
        },
        {
          "step": 180,
          "loss": 0.33674949407577515
        }
      ],
      "val_loss": 0.49003970101475713,
      "val_accuracy": 0.9019920597970486,
      "train_loss": 0.27459728029435093
    },
    {
      "epoch": 38,
      "train_steps": [
        {
          "step": 18,
          "loss": 0.2536435127258301
        },
        {
          "step": 36,
          "loss": 0.31553757190704346
        },
        {
          "step": 54,
          "loss": 0.25888973474502563
        },
        {
          "step": 72,
          "loss": 0.2795042097568512
        },
        {
          "step": 90,
          "loss": 0.22422409057617188
        },
        {
          "step": 108,
          "loss": 0.2366032600402832
        },
        {
          "step": 126,
          "loss": 0.2351062148809433
        },
        {
          "step": 144,
          "loss": 0.19609495997428894
        },
        {
          "step": 162,
          "loss": 0.2482043206691742
        },
        {
          "step": 180,
          "loss": 0.23489069938659668
        }
      ],
      "val_loss": 0.4917175568640232,
      "val_accuracy": 0.9016564886271954,
      "train_loss": 0.26594067316340364
    },
    {
      "epoch": 39,
      "train_steps": [
        {
          "step": 18,
          "loss": 0.2928355634212494
        },
        {
          "step": 36,
          "loss": 0.283914178609848
        },
        {
          "step": 54,
          "loss": 0.31179699301719666
        },
        {
          "step": 72,
          "loss": 0.22350887954235077
        },
        {
          "step": 90,
          "loss": 0.3050762414932251
        },
        {
          "step": 108,
          "loss": 0.2729034423828125
        },
        {
          "step": 126,
          "loss": 0.3102448582649231
        },
        {
          "step": 144,
          "loss": 0.36732110381126404
        },
        {
          "step": 162,
          "loss": 0.3185884356498718
        },
        {
          "step": 180,
          "loss": 0.2883630692958832
        }
      ],
      "val_loss": 0.5022173725068569,
      "val_accuracy": 0.8995565254986286,
      "train_loss": 0.27005229598802066
    },
    {
      "epoch": 40,
      "train_steps": [
        {
          "step": 18,
          "loss": 0.2482403963804245
        },
        {
          "step": 36,
          "loss": 0.2941932678222656
        },
        {
          "step": 54,
          "loss": 0.27184659242630005
        },
        {
          "step": 72,
          "loss": 0.30150729417800903
        },
        {
          "step": 90,
          "loss": 0.30668413639068604
        },
        {
          "step": 108,
          "loss": 0.2823103964328766
        },
        {
          "step": 126,
          "loss": 0.3569987416267395
        },
        {
          "step": 144,
          "loss": 0.33568549156188965
        },
        {
          "step": 162,
          "loss": 0.2227557748556137
        },
        {
          "step": 180,
          "loss": 0.17668800055980682
        }
      ],
      "val_loss": 0.5007449217140675,
      "val_accuracy": 0.8998510156571865,
      "train_loss": 0.26884018305851065
    }
  ],
  "audio_feature": "wav2vec",
  "fusion_type": "hybrid"
}