{
  "model_name": "google/electra-base-discriminator",
  "dataset": "IEMOCAP_Final",
  "experiment_type": "text",
  "epochs": 40,
  "batch_size": 16,
  "train_samples": 7025,
  "val_samples": 1506,
  "test_samples": 1506,
  "epoch_logs": [
    {
      "epoch": 1,
      "train_steps": [
        {
          "step": 44,
          "loss": 7.492980003356934
        },
        {
          "step": 88,
          "loss": 4.622769355773926
        },
        {
          "step": 132,
          "loss": 3.5914764404296875
        },
        {
          "step": 176,
          "loss": 2.4618310928344727
        },
        {
          "step": 220,
          "loss": 1.6634429693222046
        },
        {
          "step": 264,
          "loss": 1.0356851816177368
        },
        {
          "step": 308,
          "loss": 1.571821928024292
        },
        {
          "step": 352,
          "loss": 1.4230283498764038
        },
        {
          "step": 396,
          "loss": 0.9879932403564453
        },
        {
          "step": 440,
          "loss": 0.17189133167266846
        }
      ],
      "val_loss": 0.6351206189707705,
      "val_accuracy": 0.8729758762058459,
      "train_loss": 3.0082113274119116
    },
    {
      "epoch": 2,
      "train_steps": [
        {
          "step": 44,
          "loss": 0.8836908340454102
        },
        {
          "step": 88,
          "loss": 0.7344493865966797
        },
        {
          "step": 132,
          "loss": 0.7583584785461426
        },
        {
          "step": 176,
          "loss": 0.9938599467277527
        },
        {
          "step": 220,
          "loss": 0.8602432012557983
        },
        {
          "step": 264,
          "loss": 0.5474856495857239
        },
        {
          "step": 308,
          "loss": 1.0479259490966797
        },
        {
          "step": 352,
          "loss": 1.035560965538025
        },
        {
          "step": 396,
          "loss": 0.6400859951972961
        },
        {
          "step": 440,
          "loss": 0.8578799962997437
        }
      ],
      "val_loss": 0.5812744802550266,
      "val_accuracy": 0.8837451039489946,
      "train_loss": 0.9518320768394254
    },
    {
      "epoch": 3,
      "train_steps": [
        {
          "step": 44,
          "loss": 1.027513861656189
        },
        {
          "step": 88,
          "loss": 1.037574052810669
        },
        {
          "step": 132,
          "loss": 0.7211837768554688
        },
        {
          "step": 176,
          "loss": 0.759602427482605
        },
        {
          "step": 220,
          "loss": 1.0100444555282593
        },
        {
          "step": 264,
          "loss": 0.6285814642906189
        },
        {
          "step": 308,
          "loss": 0.6682707667350769
        },
        {
          "step": 352,
          "loss": 0.6610184907913208
        },
        {
          "step": 396,
          "loss": 0.6056147217750549
        },
        {
          "step": 440,
          "loss": 1.472976565361023
        }
      ],
      "val_loss": 0.5133160522109583,
      "val_accuracy": 0.8973367895578084,
      "train_loss": 0.8482881282540885
    },
    {
      "epoch": 4,
      "train_steps": [
        {
          "step": 44,
          "loss": 0.6158769130706787
        },
        {
          "step": 88,
          "loss": 0.644758939743042
        },
        {
          "step": 132,
          "loss": 0.696161150932312
        },
        {
          "step": 176,
          "loss": 0.49482762813568115
        },
        {
          "step": 220,
          "loss": 0.705451488494873
        },
        {
          "step": 264,
          "loss": 0.655769944190979
        },
        {
          "step": 308,
          "loss": 0.9826186895370483
        },
        {
          "step": 352,
          "loss": 0.6804085969924927
        },
        {
          "step": 396,
          "loss": 0.7184985876083374
        },
        {
          "step": 440,
          "loss": 0.41280683875083923
        }
      ],
      "val_loss": 0.4520052163224471,
      "val_accuracy": 0.9095989567355106,
      "train_loss": 0.7297628259116953
    },
    {
      "epoch": 5,
      "train_steps": [
        {
          "step": 44,
          "loss": 0.43605750799179077
        },
        {
          "step": 88,
          "loss": 0.5097780227661133
        },
        {
          "step": 132,
          "loss": 0.6243017911911011
        },
        {
          "step": 176,
          "loss": 0.5704978704452515
        },
        {
          "step": 220,
          "loss": 0.5231367349624634
        },
        {
          "step": 264,
          "loss": 0.4815604090690613
        },
        {
          "step": 308,
          "loss": 0.7650227546691895
        },
        {
          "step": 352,
          "loss": 0.677169680595398
        },
        {
          "step": 396,
          "loss": 0.6615114808082581
        },
        {
          "step": 440,
          "loss": 0.6121019721031189
        }
      ],
      "val_loss": 0.461212494969368,
      "val_accuracy": 0.9077575010061264,
      "train_loss": 0.6573704300278967
    },
    {
      "epoch": 6,
      "train_steps": [
        {
          "step": 44,
          "loss": 0.46934327483177185
        },
        {
          "step": 88,
          "loss": 0.5674563646316528
        },
        {
          "step": 132,
          "loss": 0.46531686186790466
        },
        {
          "step": 176,
          "loss": 0.4283030033111572
        },
        {
          "step": 220,
          "loss": 0.6428820490837097
        },
        {
          "step": 264,
          "loss": 0.7265934348106384
        },
        {
          "step": 308,
          "loss": 0.5707240104675293
        },
        {
          "step": 352,
          "loss": 0.48399949073791504
        },
        {
          "step": 396,
          "loss": 0.5739427804946899
        },
        {
          "step": 440,
          "loss": 1.594221591949463
        }
      ],
      "val_loss": 0.4322748524577994,
      "val_accuracy": 0.9135450295084401,
      "train_loss": 0.6031301738186317
    },
    {
      "epoch": 7,
      "train_steps": [
        {
          "step": 44,
          "loss": 0.45801496505737305
        },
        {
          "step": 88,
          "loss": 0.6798601150512695
        },
        {
          "step": 132,
          "loss": 0.6104519367218018
        },
        {
          "step": 176,
          "loss": 0.6550990343093872
        },
        {
          "step": 220,
          "loss": 0.5716344118118286
        },
        {
          "step": 264,
          "loss": 0.529744029045105
        },
        {
          "step": 308,
          "loss": 0.4992194175720215
        },
        {
          "step": 352,
          "loss": 0.6855454444885254
        },
        {
          "step": 396,
          "loss": 0.8511013984680176
        },
        {
          "step": 440,
          "loss": 1.1247223615646362
        }
      ],
      "val_loss": 0.43188120314949435,
      "val_accuracy": 0.9136237593701011,
      "train_loss": 0.5733275009149855
    },
    {
      "epoch": 8,
      "train_steps": [
        {
          "step": 44,
          "loss": 0.5858454704284668
        },
        {
          "step": 88,
          "loss": 0.3490593433380127
        },
        {
          "step": 132,
          "loss": 0.4660033583641052
        },
        {
          "step": 176,
          "loss": 0.5197098255157471
        },
        {
          "step": 220,
          "loss": 0.7623443603515625
        },
        {
          "step": 264,
          "loss": 0.5146675109863281
        },
        {
          "step": 308,
          "loss": 0.5664376020431519
        },
        {
          "step": 352,
          "loss": 0.43664225935935974
        },
        {
          "step": 396,
          "loss": 0.6156330704689026
        },
        {
          "step": 440,
          "loss": 0.4518077075481415
        }
      ],
      "val_loss": 0.4302129050618724,
      "val_accuracy": 0.9139574189876255,
      "train_loss": 0.5359595149755478
    },
    {
      "epoch": 9,
      "train_steps": [
        {
          "step": 44,
          "loss": 0.43004295229911804
        },
        {
          "step": 88,
          "loss": 0.43863174319267273
        },
        {
          "step": 132,
          "loss": 0.5018242597579956
        },
        {
          "step": 176,
          "loss": 0.609494149684906
        },
        {
          "step": 220,
          "loss": 0.666282594203949
        },
        {
          "step": 264,
          "loss": 0.3961330056190491
        },
        {
          "step": 308,
          "loss": 0.5115325450897217
        },
        {
          "step": 352,
          "loss": 0.5005830526351929
        },
        {
          "step": 396,
          "loss": 0.7122675180435181
        },
        {
          "step": 440,
          "loss": 0.5543222427368164
        }
      ],
      "val_loss": 0.43450583627349454,
      "val_accuracy": 0.9130988327453011,
      "train_loss": 0.5066345127130096
    },
    {
      "epoch": 10,
      "train_steps": [
        {
          "step": 44,
          "loss": 0.345822274684906
        },
        {
          "step": 88,
          "loss": 0.35362106561660767
        },
        {
          "step": 132,
          "loss": 0.5712293386459351
        },
        {
          "step": 176,
          "loss": 0.31483158469200134
        },
        {
          "step": 220,
          "loss": 0.49584031105041504
        },
        {
          "step": 264,
          "loss": 0.570804238319397
        },
        {
          "step": 308,
          "loss": 0.40276262164115906
        },
        {
          "step": 352,
          "loss": 0.5780858397483826
        },
        {
          "step": 396,
          "loss": 0.3707190155982971
        },
        {
          "step": 440,
          "loss": 0.9076692461967468
        }
      ],
      "val_loss": 0.43208746423846794,
      "val_accuracy": 0.9135825071523064,
      "train_loss": 0.4760947889563712
    },
    {
      "epoch": 11,
      "train_steps": [
        {
          "step": 44,
          "loss": 0.4386928677558899
        },
        {
          "step": 88,
          "loss": 0.5972766876220703
        },
        {
          "step": 132,
          "loss": 0.5876150131225586
        },
        {
          "step": 176,
          "loss": 0.35624009370803833
        },
        {
          "step": 220,
          "loss": 0.6135941743850708
        },
        {
          "step": 264,
          "loss": 0.4981096386909485
        },
        {
          "step": 308,
          "loss": 0.6159120798110962
        },
        {
          "step": 352,
          "loss": 0.32616615295410156
        },
        {
          "step": 396,
          "loss": 0.6759951114654541
        },
        {
          "step": 440,
          "loss": 0.14194536209106445
        }
      ],
      "val_loss": 0.4259676250972246,
      "val_accuracy": 0.9148064749805551,
      "train_loss": 0.46387409733777696
    },
    {
      "epoch": 12,
      "train_steps": [
        {
          "step": 44,
          "loss": 0.5616532564163208
        },
        {
          "step": 88,
          "loss": 0.3794425427913666
        },
        {
          "step": 132,
          "loss": 0.5508890151977539
        },
        {
          "step": 176,
          "loss": 0.6657922267913818
        },
        {
          "step": 220,
          "loss": 0.4618384838104248
        },
        {
          "step": 264,
          "loss": 0.5912649631500244
        },
        {
          "step": 308,
          "loss": 0.43342214822769165
        },
        {
          "step": 352,
          "loss": 0.50345379114151
        },
        {
          "step": 396,
          "loss": 0.1481332778930664
        },
        {
          "step": 440,
          "loss": 0.4497356116771698
        }
      ],
      "val_loss": 0.43286568836161965,
      "val_accuracy": 0.9134268623276761,
      "train_loss": 0.4459630896421996
    },
    {
      "epoch": 13,
      "train_steps": [
        {
          "step": 44,
          "loss": 0.30250638723373413
        },
        {
          "step": 88,
          "loss": 0.28503257036209106
        },
        {
          "step": 132,
          "loss": 0.46618008613586426
        },
        {
          "step": 176,
          "loss": 0.38775190711021423
        },
        {
          "step": 220,
          "loss": 0.28097808361053467
        },
        {
          "step": 264,
          "loss": 0.33790144324302673
        },
        {
          "step": 308,
          "loss": 0.5023367404937744
        },
        {
          "step": 352,
          "loss": 0.34530267119407654
        },
        {
          "step": 396,
          "loss": 0.5639654397964478
        },
        {
          "step": 440,
          "loss": 0.553306519985199
        }
      ],
      "val_loss": 0.4736262459503977,
      "val_accuracy": 0.9052747508099205,
      "train_loss": 0.4169021307744763
    },
    {
      "epoch": 14,
      "train_steps": [
        {
          "step": 44,
          "loss": 0.4458201825618744
        },
        {
          "step": 88,
          "loss": 0.49497660994529724
        },
        {
          "step": 132,
          "loss": 0.5420119762420654
        },
        {
          "step": 176,
          "loss": 0.32975083589553833
        },
        {
          "step": 220,
          "loss": 0.3701414465904236
        },
        {
          "step": 264,
          "loss": 0.3173569440841675
        },
        {
          "step": 308,
          "loss": 0.319149911403656
        },
        {
          "step": 352,
          "loss": 0.47535181045532227
        },
        {
          "step": 396,
          "loss": 0.4743419587612152
        },
        {
          "step": 440,
          "loss": 0.06140751391649246
        }
      ],
      "val_loss": 0.4651976094434136,
      "val_accuracy": 0.9069604781113173,
      "train_loss": 0.4137089153413068
    },
    {
      "epoch": 15,
      "train_steps": [
        {
          "step": 44,
          "loss": 0.42719608545303345
        },
        {
          "step": 88,
          "loss": 0.35515090823173523
        },
        {
          "step": 132,
          "loss": 0.35041889548301697
        },
        {
          "step": 176,
          "loss": 0.4033464789390564
        },
        {
          "step": 220,
          "loss": 0.30964338779449463
        },
        {
          "step": 264,
          "loss": 0.3566299378871918
        },
        {
          "step": 308,
          "loss": 0.5178424715995789
        },
        {
          "step": 352,
          "loss": 0.4372478723526001
        },
        {
          "step": 396,
          "loss": 0.418948769569397
        },
        {
          "step": 440,
          "loss": 0.10752828419208527
        }
      ],
      "val_loss": 0.47098107620289453,
      "val_accuracy": 0.9058037847594211,
      "train_loss": 0.3949809248474511
    },
    {
      "epoch": 16,
      "train_steps": [
        {
          "step": 44,
          "loss": 0.45207592844963074
        },
        {
          "step": 88,
          "loss": 0.3485001027584076
        },
        {
          "step": 132,
          "loss": 0.3822501599788666
        },
        {
          "step": 176,
          "loss": 0.3597784638404846
        },
        {
          "step": 220,
          "loss": 0.33176228404045105
        },
        {
          "step": 264,
          "loss": 0.24225246906280518
        },
        {
          "step": 308,
          "loss": 0.5299583673477173
        },
        {
          "step": 352,
          "loss": 0.5450502634048462
        },
        {
          "step": 396,
          "loss": 0.41686052083969116
        },
        {
          "step": 440,
          "loss": 0.900267481803894
        }
      ],
      "val_loss": 0.4622949266120007,
      "val_accuracy": 0.9075410146775998,
      "train_loss": 0.3804473745890639
    },
    {
      "epoch": 17,
      "train_steps": [
        {
          "step": 44,
          "loss": 0.2875070571899414
        },
        {
          "step": 88,
          "loss": 0.3521406650543213
        },
        {
          "step": 132,
          "loss": 0.2211294174194336
        },
        {
          "step": 176,
          "loss": 0.39492902159690857
        },
        {
          "step": 220,
          "loss": 0.34313473105430603
        },
        {
          "step": 264,
          "loss": 0.27964723110198975
        },
        {
          "step": 308,
          "loss": 0.36193475127220154
        },
        {
          "step": 352,
          "loss": 0.4373686909675598
        },
        {
          "step": 396,
          "loss": 0.31676098704338074
        },
        {
          "step": 440,
          "loss": 0.24769800901412964
        }
      ],
      "val_loss": 0.45906886254486284,
      "val_accuracy": 0.9081862274910274,
      "train_loss": 0.37580338106914
    },
    {
      "epoch": 18,
      "train_steps": [
        {
          "step": 44,
          "loss": 0.4122666120529175
        },
        {
          "step": 88,
          "loss": 0.5327868461608887
        },
        {
          "step": 132,
          "loss": 0.5088945627212524
        },
        {
          "step": 176,
          "loss": 0.23031434416770935
        },
        {
          "step": 220,
          "loss": 0.4500546455383301
        },
        {
          "step": 264,
          "loss": 0.45846301317214966
        },
        {
          "step": 308,
          "loss": 0.3125256299972534
        },
        {
          "step": 352,
          "loss": 0.2263314425945282
        },
        {
          "step": 396,
          "loss": 0.546059787273407
        },
        {
          "step": 440,
          "loss": 0.029146708548069
        }
      ],
      "val_loss": 0.45669413852064233,
      "val_accuracy": 0.9086611722958715,
      "train_loss": 0.3593090083280748
    },
    {
      "epoch": 19,
      "train_steps": [
        {
          "step": 44,
          "loss": 0.2663155496120453
        },
        {
          "step": 88,
          "loss": 0.40833720564842224
        },
        {
          "step": 132,
          "loss": 0.3178059458732605
        },
        {
          "step": 176,
          "loss": 0.4383350610733032
        },
        {
          "step": 220,
          "loss": 0.4028187394142151
        },
        {
          "step": 264,
          "loss": 0.19333383440971375
        },
        {
          "step": 308,
          "loss": 0.35796865820884705
        },
        {
          "step": 352,
          "loss": 0.2751619517803192
        },
        {
          "step": 396,
          "loss": 0.47111088037490845
        },
        {
          "step": 440,
          "loss": 0.07087233662605286
        }
      ],
      "val_loss": 0.457769177305071,
      "val_accuracy": 0.9084461645389859,
      "train_loss": 0.35730422223833475
    },
    {
      "epoch": 20,
      "train_steps": [
        {
          "step": 44,
          "loss": 0.2566613554954529
        },
        {
          "step": 88,
          "loss": 0.4903852939605713
        },
        {
          "step": 132,
          "loss": 0.35007357597351074
        },
        {
          "step": 176,
          "loss": 0.3017424941062927
        },
        {
          "step": 220,
          "loss": 0.39399322867393494
        },
        {
          "step": 264,
          "loss": 0.32666659355163574
        },
        {
          "step": 308,
          "loss": 0.3649160861968994
        },
        {
          "step": 352,
          "loss": 0.3147481381893158
        },
        {
          "step": 396,
          "loss": 0.3767967224121094
        },
        {
          "step": 440,
          "loss": 0.7784475088119507
        }
      ],
      "val_loss": 0.4680420770456916,
      "val_accuracy": 0.9063915845908617,
      "train_loss": 0.34292122088372706
    },
    {
      "epoch": 21,
      "train_steps": [
        {
          "step": 44,
          "loss": 0.2531641721725464
        },
        {
          "step": 88,
          "loss": 0.3712356984615326
        },
        {
          "step": 132,
          "loss": 0.3472190499305725
        },
        {
          "step": 176,
          "loss": 0.34109675884246826
        },
        {
          "step": 220,
          "loss": 0.5422964692115784
        },
        {
          "step": 264,
          "loss": 0.5023894309997559
        },
        {
          "step": 308,
          "loss": 0.21560120582580566
        },
        {
          "step": 352,
          "loss": 0.47181421518325806
        },
        {
          "step": 396,
          "loss": 0.2983560860157013
        },
        {
          "step": 440,
          "loss": 0.4065645933151245
        }
      ],
      "val_loss": 0.49664817342632694,
      "val_accuracy": 0.9006703653147347,
      "train_loss": 0.3339530279690569
    },
    {
      "epoch": 22,
      "train_steps": [
        {
          "step": 44,
          "loss": 0.17761144042015076
        },
        {
          "step": 88,
          "loss": 0.4204384684562683
        },
        {
          "step": 132,
          "loss": 0.36834046244621277
        },
        {
          "step": 176,
          "loss": 0.3036106824874878
        },
        {
          "step": 220,
          "loss": 0.36692070960998535
        },
        {
          "step": 264,
          "loss": 0.495792031288147
        },
        {
          "step": 308,
          "loss": 0.22772535681724548
        },
        {
          "step": 352,
          "loss": 0.27756351232528687
        },
        {
          "step": 396,
          "loss": 0.2937227487564087
        },
        {
          "step": 440,
          "loss": 0.5226053595542908
        }
      ],
      "val_loss": 0.4648687699907704,
      "val_accuracy": 0.9070262460018459,
      "train_loss": 0.32195472304116596
    },
    {
      "epoch": 23,
      "train_steps": [
        {
          "step": 44,
          "loss": 0.33266472816467285
        },
        {
          "step": 88,
          "loss": 0.2576950788497925
        },
        {
          "step": 132,
          "loss": 0.46088361740112305
        },
        {
          "step": 176,
          "loss": 0.3052305281162262
        },
        {
          "step": 220,
          "loss": 0.2777186334133148
        },
        {
          "step": 264,
          "loss": 0.25811848044395447
        },
        {
          "step": 308,
          "loss": 0.44728749990463257
        },
        {
          "step": 352,
          "loss": 0.2330673187971115
        },
        {
          "step": 396,
          "loss": 0.3335956335067749
        },
        {
          "step": 440,
          "loss": 0.1098853200674057
        }
      ],
      "val_loss": 0.4615775045595671,
      "val_accuracy": 0.9076844990880866,
      "train_loss": 0.32275328981605445
    },
    {
      "epoch": 24,
      "train_steps": [
        {
          "step": 44,
          "loss": 0.21324293315410614
        },
        {
          "step": 88,
          "loss": 0.2981984615325928
        },
        {
          "step": 132,
          "loss": 0.35448241233825684
        },
        {
          "step": 176,
          "loss": 0.2998572587966919
        },
        {
          "step": 220,
          "loss": 0.32347139716148376
        },
        {
          "step": 264,
          "loss": 0.22124545276165009
        },
        {
          "step": 308,
          "loss": 0.2540883719921112
        },
        {
          "step": 352,
          "loss": 0.3202647864818573
        },
        {
          "step": 396,
          "loss": 0.2706143260002136
        },
        {
          "step": 440,
          "loss": 1.3559257984161377
        }
      ],
      "val_loss": 0.4624286957477268,
      "val_accuracy": 0.9075142608504546,
      "train_loss": 0.3126467399299145
    },
    {
      "epoch": 25,
      "train_steps": [
        {
          "step": 44,
          "loss": 0.3198637366294861
        },
        {
          "step": 88,
          "loss": 0.45505663752555847
        },
        {
          "step": 132,
          "loss": 0.2552778720855713
        },
        {
          "step": 176,
          "loss": 0.2518441379070282
        },
        {
          "step": 220,
          "loss": 0.20710411667823792
        },
        {
          "step": 264,
          "loss": 0.26279985904693604
        },
        {
          "step": 308,
          "loss": 0.2283208817243576
        },
        {
          "step": 352,
          "loss": 0.3567527234554291
        },
        {
          "step": 396,
          "loss": 0.19228479266166687
        },
        {
          "step": 440,
          "loss": 0.17267149686813354
        }
      ],
      "val_loss": 0.4880968020150536,
      "val_accuracy": 0.9023806395969893,
      "train_loss": 0.3041959488595074
    },
    {
      "epoch": 26,
      "train_steps": [
        {
          "step": 44,
          "loss": 0.2760951519012451
        },
        {
          "step": 88,
          "loss": 0.28338131308555603
        },
        {
          "step": 132,
          "loss": 0.46970653533935547
        },
        {
          "step": 176,
          "loss": 0.19868645071983337
        },
        {
          "step": 220,
          "loss": 0.31936442852020264
        },
        {
          "step": 264,
          "loss": 0.2628566026687622
        },
        {
          "step": 308,
          "loss": 0.33726704120635986
        },
        {
          "step": 352,
          "loss": 0.23756438493728638
        },
        {
          "step": 396,
          "loss": 0.3878006637096405
        },
        {
          "step": 440,
          "loss": 0.6831716299057007
        }
      ],
      "val_loss": 0.474025370259034,
      "val_accuracy": 0.9051949259481932,
      "train_loss": 0.303568685291843
    },
    {
      "epoch": 27,
      "train_steps": [
        {
          "step": 44,
          "loss": 0.21388030052185059
        },
        {
          "step": 88,
          "loss": 0.22457429766654968
        },
        {
          "step": 132,
          "loss": 0.281880259513855
        },
        {
          "step": 176,
          "loss": 0.29580777883529663
        },
        {
          "step": 220,
          "loss": 0.17470864951610565
        },
        {
          "step": 264,
          "loss": 0.3847235143184662
        },
        {
          "step": 308,
          "loss": 0.38604411482810974
        },
        {
          "step": 352,
          "loss": 0.26706477999687195
        },
        {
          "step": 396,
          "loss": 0.24978455901145935
        },
        {
          "step": 440,
          "loss": 0.03461313247680664
        }
      ],
      "val_loss": 0.48019900118049824,
      "val_accuracy": 0.9039601997639004,
      "train_loss": 0.2867053664882075
    },
    {
      "epoch": 28,
      "train_steps": [
        {
          "step": 44,
          "loss": 0.22723834216594696
        },
        {
          "step": 88,
          "loss": 0.3870614171028137
        },
        {
          "step": 132,
          "loss": 0.23402492702007294
        },
        {
          "step": 176,
          "loss": 0.2755325734615326
        },
        {
          "step": 220,
          "loss": 0.30448901653289795
        },
        {
          "step": 264,
          "loss": 0.31175464391708374
        },
        {
          "step": 308,
          "loss": 0.43389028310775757
        },
        {
          "step": 352,
          "loss": 0.2315671294927597
        },
        {
          "step": 396,
          "loss": 0.3991006016731262
        },
        {
          "step": 440,
          "loss": 0.2730063199996948
        }
      ],
      "val_loss": 0.4743682318612149,
      "val_accuracy": 0.9051263536277571,
      "train_loss": 0.2858646048402244
    },
    {
      "epoch": 29,
      "train_steps": [
        {
          "step": 44,
          "loss": 0.3899179697036743
        },
        {
          "step": 88,
          "loss": 0.25651535391807556
        },
        {
          "step": 132,
          "loss": 0.3284844756126404
        },
        {
          "step": 176,
          "loss": 0.25295767188072205
        },
        {
          "step": 220,
          "loss": 0.348552942276001
        },
        {
          "step": 264,
          "loss": 0.32474395632743835
        },
        {
          "step": 308,
          "loss": 0.3000098764896393
        },
        {
          "step": 352,
          "loss": 0.3225242495536804
        },
        {
          "step": 396,
          "loss": 0.2527339458465576
        },
        {
          "step": 440,
          "loss": 0.16631083190441132
        }
      ],
      "val_loss": 0.4816812072929583,
      "val_accuracy": 0.9036637585414083,
      "train_loss": 0.2841521177102219
    },
    {
      "epoch": 30,
      "train_steps": [
        {
          "step": 44,
          "loss": 0.20233428478240967
        },
        {
          "step": 88,
          "loss": 0.3143726587295532
        },
        {
          "step": 132,
          "loss": 0.28833484649658203
        },
        {
          "step": 176,
          "loss": 0.33637699484825134
        },
        {
          "step": 220,
          "loss": 0.2569519281387329
        },
        {
          "step": 264,
          "loss": 0.30747562646865845
        },
        {
          "step": 308,
          "loss": 0.2618240714073181
        },
        {
          "step": 352,
          "loss": 0.2533239722251892
        },
        {
          "step": 396,
          "loss": 0.23189818859100342
        },
        {
          "step": 440,
          "loss": 0.5752329230308533
        }
      ],
      "val_loss": 0.4783421654450266,
      "val_accuracy": 0.9043315669109947,
      "train_loss": 0.2836595172062516
    },
    {
      "epoch": 31,
      "train_steps": [
        {
          "step": 44,
          "loss": 0.19287066161632538
        },
        {
          "step": 88,
          "loss": 0.354818195104599
        },
        {
          "step": 132,
          "loss": 0.36160337924957275
        },
        {
          "step": 176,
          "loss": 0.2996217608451843
        },
        {
          "step": 220,
          "loss": 0.2679343521595001
        },
        {
          "step": 264,
          "loss": 0.18831783533096313
        },
        {
          "step": 308,
          "loss": 0.23234325647354126
        },
        {
          "step": 352,
          "loss": 0.33461952209472656
        },
        {
          "step": 396,
          "loss": 0.25623607635498047
        },
        {
          "step": 440,
          "loss": 0.32421407103538513
        }
      ],
      "val_loss": 0.4737878918647766,
      "val_accuracy": 0.9052424216270447,
      "train_loss": 0.2744787393815138
    },
    {
      "epoch": 32,
      "train_steps": [
        {
          "step": 44,
          "loss": 0.30059778690338135
        },
        {
          "step": 88,
          "loss": 0.16238506138324738
        },
        {
          "step": 132,
          "loss": 0.3710429072380066
        },
        {
          "step": 176,
          "loss": 0.19556443393230438
        },
        {
          "step": 220,
          "loss": 0.2531856894493103
        },
        {
          "step": 264,
          "loss": 0.28552019596099854
        },
        {
          "step": 308,
          "loss": 0.26236656308174133
        },
        {
          "step": 352,
          "loss": 0.28050655126571655
        },
        {
          "step": 396,
          "loss": 0.19536978006362915
        },
        {
          "step": 440,
          "loss": 0.21562252938747406
        }
      ],
      "val_loss": 0.4826741088377802,
      "val_accuracy": 0.903465178232444,
      "train_loss": 0.2713444411923939
    },
    {
      "epoch": 33,
      "train_steps": [
        {
          "step": 44,
          "loss": 0.1989862620830536
        },
        {
          "step": 88,
          "loss": 0.447026789188385
        },
        {
          "step": 132,
          "loss": 0.15273043513298035
        },
        {
          "step": 176,
          "loss": 0.4224240779876709
        },
        {
          "step": 220,
          "loss": 0.20112189650535583
        },
        {
          "step": 264,
          "loss": 0.24975991249084473
        },
        {
          "step": 308,
          "loss": 0.3243494927883148
        },
        {
          "step": 352,
          "loss": 0.22991430759429932
        },
        {
          "step": 396,
          "loss": 0.2663862407207489
        },
        {
          "step": 440,
          "loss": 0.05223964899778366
        }
      ],
      "val_loss": 0.47611503475590755,
      "val_accuracy": 0.9047769930488185,
      "train_loss": 0.2678143906999718
    },
    {
      "epoch": 34,
      "train_steps": [
        {
          "step": 44,
          "loss": 0.2205178141593933
        },
        {
          "step": 88,
          "loss": 0.27822625637054443
        },
        {
          "step": 132,
          "loss": 0.32133251428604126
        },
        {
          "step": 176,
          "loss": 0.27106428146362305
        },
        {
          "step": 220,
          "loss": 0.4421192407608032
        },
        {
          "step": 264,
          "loss": 0.15469971299171448
        },
        {
          "step": 308,
          "loss": 0.31815585494041443
        },
        {
          "step": 352,
          "loss": 0.26768675446510315
        },
        {
          "step": 396,
          "loss": 0.28715285658836365
        },
        {
          "step": 440,
          "loss": 0.5014575123786926
        }
      ],
      "val_loss": 0.5013149866932317,
      "val_accuracy": 0.8997370026613537,
      "train_loss": 0.26424241186204284
    },
    {
      "epoch": 35,
      "train_steps": [
        {
          "step": 44,
          "loss": 0.2700674533843994
        },
        {
          "step": 88,
          "loss": 0.31561335921287537
        },
        {
          "step": 132,
          "loss": 0.3651340901851654
        },
        {
          "step": 176,
          "loss": 0.42915821075439453
        },
        {
          "step": 220,
          "loss": 0.25467514991760254
        },
        {
          "step": 264,
          "loss": 0.2985457181930542
        },
        {
          "step": 308,
          "loss": 0.3506045341491699
        },
        {
          "step": 352,
          "loss": 0.2044496238231659
        },
        {
          "step": 396,
          "loss": 0.31458190083503723
        },
        {
          "step": 440,
          "loss": 0.6126177310943604
        }
      ],
      "val_loss": 0.4960240254276677,
      "val_accuracy": 0.9007951949144665,
      "train_loss": 0.2622336576777426
    },
    {
      "epoch": 36,
      "train_steps": [
        {
          "step": 44,
          "loss": 0.22302207350730896
        },
        {
          "step": 88,
          "loss": 0.19595710933208466
        },
        {
          "step": 132,
          "loss": 0.2783733010292053
        },
        {
          "step": 176,
          "loss": 0.34021657705307007
        },
        {
          "step": 220,
          "loss": 0.23868702352046967
        },
        {
          "step": 264,
          "loss": 0.24603763222694397
        },
        {
          "step": 308,
          "loss": 0.2600965201854706
        },
        {
          "step": 352,
          "loss": 0.17060714960098267
        },
        {
          "step": 396,
          "loss": 0.22528867423534393
        },
        {
          "step": 440,
          "loss": 0.046835049986839294
        }
      ],
      "val_loss": 0.49668583399371097,
      "val_accuracy": 0.9006628332012578,
      "train_loss": 0.26352788091383195
    },
    {
      "epoch": 37,
      "train_steps": [
        {
          "step": 44,
          "loss": 0.3094298243522644
        },
        {
          "step": 88,
          "loss": 0.2268548607826233
        },
        {
          "step": 132,
          "loss": 0.2058490812778473
        },
        {
          "step": 176,
          "loss": 0.21318817138671875
        },
        {
          "step": 220,
          "loss": 0.197629913687706
        },
        {
          "step": 264,
          "loss": 0.22789478302001953
        },
        {
          "step": 308,
          "loss": 0.22361502051353455
        },
        {
          "step": 352,
          "loss": 0.2735103666782379
        },
        {
          "step": 396,
          "loss": 0.4462810456752777
        },
        {
          "step": 440,
          "loss": 0.11185895651578903
        }
      ],
      "val_loss": 0.475860365440971,
      "val_accuracy": 0.9048279269118058,
      "train_loss": 0.2543733660470356
    },
    {
      "epoch": 38,
      "train_steps": [
        {
          "step": 44,
          "loss": 0.28922492265701294
        },
        {
          "step": 88,
          "loss": 0.12763983011245728
        },
        {
          "step": 132,
          "loss": 0.22383001446723938
        },
        {
          "step": 176,
          "loss": 0.2529675364494324
        },
        {
          "step": 220,
          "loss": 0.17231176793575287
        },
        {
          "step": 264,
          "loss": 0.1950669139623642
        },
        {
          "step": 308,
          "loss": 0.5452132225036621
        },
        {
          "step": 352,
          "loss": 0.34398144483566284
        },
        {
          "step": 396,
          "loss": 0.16521847248077393
        },
        {
          "step": 440,
          "loss": 0.14669935405254364
        }
      ],
      "val_loss": 0.4750899716427452,
      "val_accuracy": 0.9049820056714509,
      "train_loss": 0.2540954074060375
    },
    {
      "epoch": 39,
      "train_steps": [
        {
          "step": 44,
          "loss": 0.2604963779449463
        },
        {
          "step": 88,
          "loss": 0.2547193169593811
        },
        {
          "step": 132,
          "loss": 0.44078516960144043
        },
        {
          "step": 176,
          "loss": 0.24901895225048065
        },
        {
          "step": 220,
          "loss": 0.2580181062221527
        },
        {
          "step": 264,
          "loss": 0.23686760663986206
        },
        {
          "step": 308,
          "loss": 0.1628401279449463
        },
        {
          "step": 352,
          "loss": 0.21786457300186157
        },
        {
          "step": 396,
          "loss": 0.2002609372138977
        },
        {
          "step": 440,
          "loss": 0.3920856714248657
        }
      ],
      "val_loss": 0.5001011271225778,
      "val_accuracy": 0.8999797745754844,
      "train_loss": 0.25039015151560307
    },
    {
      "epoch": 40,
      "train_steps": [
        {
          "step": 44,
          "loss": 0.23740564286708832
        },
        {
          "step": 88,
          "loss": 0.2654682993888855
        },
        {
          "step": 132,
          "loss": 0.2450411021709442
        },
        {
          "step": 176,
          "loss": 0.19423845410346985
        },
        {
          "step": 220,
          "loss": 0.28816697001457214
        },
        {
          "step": 264,
          "loss": 0.43007928133010864
        },
        {
          "step": 308,
          "loss": 0.1672736257314682
        },
        {
          "step": 352,
          "loss": 0.32398721575737
        },
        {
          "step": 396,
          "loss": 0.20361727476119995
        },
        {
          "step": 440,
          "loss": 0.2801598310470581
        }
      ],
      "val_loss": 0.47034990285572253,
      "val_accuracy": 0.9059300194288555,
      "train_loss": 0.25267262402921914
    }
  ],
  "final_metrics": {
    "Test Loss": 0.47090671140896645,
    "Valence": {
      "MSE": 0.45286375284194946,
      "RMSE": 0.6729515233967076,
      "MAE": 0.5059118866920471,
      "R2": 0.43445491790771484
    },
    "Arousal": {
      "MSE": 0.4193058907985687,
      "RMSE": 0.6475383315283881,
      "MAE": 0.510358452796936,
      "R2": 0.14016318321228027
    },
    "Dominance": {
      "MSE": 0.5502191185951233,
      "RMSE": 0.7417675637254053,
      "MAE": 0.5830182433128357,
      "R2": 0.09675508737564087
    }
  }
}