{
  "model_name": "microsoft/deberta-v3-base",
  "dataset": "IEMOCAP_Final",
  "experiment_type": "multimodal",
  "epochs": 40,
  "batch_size": 32,
  "train_samples": 7025,
  "val_samples": 1506,
  "test_samples": 1506,
  "epoch_logs": [
    {
      "epoch": 1,
      "train_steps": [
        {
          "step": 22,
          "loss": 8.976728439331055
        },
        {
          "step": 44,
          "loss": 5.147368907928467
        },
        {
          "step": 66,
          "loss": 3.662299871444702
        },
        {
          "step": 88,
          "loss": 2.7226858139038086
        },
        {
          "step": 110,
          "loss": 1.8045384883880615
        },
        {
          "step": 132,
          "loss": 1.514577865600586
        },
        {
          "step": 154,
          "loss": 1.2635353803634644
        },
        {
          "step": 176,
          "loss": 1.274199366569519
        },
        {
          "step": 198,
          "loss": 0.7879732847213745
        },
        {
          "step": 220,
          "loss": 1.113442301750183
        }
      ],
      "val_loss": 0.6596964877098799,
      "val_accuracy": 0.868060702458024,
      "train_loss": 3.2054278948090293
    },
    {
      "epoch": 2,
      "train_steps": [
        {
          "step": 22,
          "loss": 1.0897107124328613
        },
        {
          "step": 44,
          "loss": 1.0184249877929688
        },
        {
          "step": 66,
          "loss": 0.9516298174858093
        },
        {
          "step": 88,
          "loss": 1.2640291452407837
        },
        {
          "step": 110,
          "loss": 0.985924243927002
        },
        {
          "step": 132,
          "loss": 0.921707808971405
        },
        {
          "step": 154,
          "loss": 1.1403992176055908
        },
        {
          "step": 176,
          "loss": 0.8725702166557312
        },
        {
          "step": 198,
          "loss": 0.8305978775024414
        },
        {
          "step": 220,
          "loss": 0.9373635053634644
        }
      ],
      "val_loss": 0.6064770227919022,
      "val_accuracy": 0.8787045954416196,
      "train_loss": 0.9840283353220333
    },
    {
      "epoch": 3,
      "train_steps": [
        {
          "step": 22,
          "loss": 0.7677440643310547
        },
        {
          "step": 44,
          "loss": 0.7786935567855835
        },
        {
          "step": 66,
          "loss": 0.8114403486251831
        },
        {
          "step": 88,
          "loss": 0.764957070350647
        },
        {
          "step": 110,
          "loss": 1.0420727729797363
        },
        {
          "step": 132,
          "loss": 1.1147568225860596
        },
        {
          "step": 154,
          "loss": 0.9724647402763367
        },
        {
          "step": 176,
          "loss": 0.8515893816947937
        },
        {
          "step": 198,
          "loss": 0.7880648374557495
        },
        {
          "step": 220,
          "loss": 0.9947378635406494
        }
      ],
      "val_loss": 0.5071201231330633,
      "val_accuracy": 0.8985759753733873,
      "train_loss": 0.8876976866613735
    },
    {
      "epoch": 4,
      "train_steps": [
        {
          "step": 22,
          "loss": 0.8970843553543091
        },
        {
          "step": 44,
          "loss": 0.7823275327682495
        },
        {
          "step": 66,
          "loss": 0.771967351436615
        },
        {
          "step": 88,
          "loss": 0.6949516534805298
        },
        {
          "step": 110,
          "loss": 0.9295966029167175
        },
        {
          "step": 132,
          "loss": 0.7493103742599487
        },
        {
          "step": 154,
          "loss": 0.8663233518600464
        },
        {
          "step": 176,
          "loss": 0.8632626533508301
        },
        {
          "step": 198,
          "loss": 0.7635950446128845
        },
        {
          "step": 220,
          "loss": 0.6629716753959656
        }
      ],
      "val_loss": 0.48883803685506183,
      "val_accuracy": 0.9022323926289877,
      "train_loss": 0.804755779423497
    },
    {
      "epoch": 5,
      "train_steps": [
        {
          "step": 22,
          "loss": 0.8618036508560181
        },
        {
          "step": 44,
          "loss": 0.6129488945007324
        },
        {
          "step": 66,
          "loss": 0.9001001715660095
        },
        {
          "step": 88,
          "loss": 0.8275197744369507
        },
        {
          "step": 110,
          "loss": 0.6689825057983398
        },
        {
          "step": 132,
          "loss": 0.7295956015586853
        },
        {
          "step": 154,
          "loss": 0.7767969965934753
        },
        {
          "step": 176,
          "loss": 0.6090101599693298
        },
        {
          "step": 198,
          "loss": 0.6618760824203491
        },
        {
          "step": 220,
          "loss": 0.8029428124427795
        }
      ],
      "val_loss": 0.4872080571949482,
      "val_accuracy": 0.9025583885610103,
      "train_loss": 0.7354690450158986
    },
    {
      "epoch": 6,
      "train_steps": [
        {
          "step": 22,
          "loss": 0.741398811340332
        },
        {
          "step": 44,
          "loss": 0.7033748030662537
        },
        {
          "step": 66,
          "loss": 0.7925597429275513
        },
        {
          "step": 88,
          "loss": 0.659174382686615
        },
        {
          "step": 110,
          "loss": 0.6225467324256897
        },
        {
          "step": 132,
          "loss": 0.5554931163787842
        },
        {
          "step": 154,
          "loss": 0.577433705329895
        },
        {
          "step": 176,
          "loss": 0.7184447050094604
        },
        {
          "step": 198,
          "loss": 0.6627060174942017
        },
        {
          "step": 220,
          "loss": 0.4183255434036255
        }
      ],
      "val_loss": 0.4400988270839055,
      "val_accuracy": 0.9119802345832189,
      "train_loss": 0.6849393313581293
    },
    {
      "epoch": 7,
      "train_steps": [
        {
          "step": 22,
          "loss": 0.5801437497138977
        },
        {
          "step": 44,
          "loss": 0.5409088134765625
        },
        {
          "step": 66,
          "loss": 0.671480655670166
        },
        {
          "step": 88,
          "loss": 0.5321135520935059
        },
        {
          "step": 110,
          "loss": 0.5914560556411743
        },
        {
          "step": 132,
          "loss": 0.7773733139038086
        },
        {
          "step": 154,
          "loss": 0.7262670397758484
        },
        {
          "step": 176,
          "loss": 0.7497326731681824
        },
        {
          "step": 198,
          "loss": 0.8312649726867676
        },
        {
          "step": 220,
          "loss": 0.7748779654502869
        }
      ],
      "val_loss": 0.4305585039158662,
      "val_accuracy": 0.9138882992168268,
      "train_loss": 0.6442371216687289
    },
    {
      "epoch": 8,
      "train_steps": [
        {
          "step": 22,
          "loss": 0.7059314250946045
        },
        {
          "step": 44,
          "loss": 0.639595627784729
        },
        {
          "step": 66,
          "loss": 0.4784189462661743
        },
        {
          "step": 88,
          "loss": 0.7439226508140564
        },
        {
          "step": 110,
          "loss": 0.561670184135437
        },
        {
          "step": 132,
          "loss": 0.546628475189209
        },
        {
          "step": 154,
          "loss": 0.6594241857528687
        },
        {
          "step": 176,
          "loss": 0.6463054418563843
        },
        {
          "step": 198,
          "loss": 0.568687379360199
        },
        {
          "step": 220,
          "loss": 0.5278627276420593
        }
      ],
      "val_loss": 0.441659373541673,
      "val_accuracy": 0.9116681252916654,
      "train_loss": 0.6143065158616413
    },
    {
      "epoch": 9,
      "train_steps": [
        {
          "step": 22,
          "loss": 0.7507603168487549
        },
        {
          "step": 44,
          "loss": 0.6573491096496582
        },
        {
          "step": 66,
          "loss": 0.5570729970932007
        },
        {
          "step": 88,
          "loss": 0.641568660736084
        },
        {
          "step": 110,
          "loss": 0.47784996032714844
        },
        {
          "step": 132,
          "loss": 0.5843299031257629
        },
        {
          "step": 154,
          "loss": 0.6296833753585815
        },
        {
          "step": 176,
          "loss": 0.6110711097717285
        },
        {
          "step": 198,
          "loss": 0.5694093108177185
        },
        {
          "step": 220,
          "loss": 0.602280855178833
        }
      ],
      "val_loss": 0.42498528957366943,
      "val_accuracy": 0.9150029420852661,
      "train_loss": 0.6013354587284001
    },
    {
      "epoch": 10,
      "train_steps": [
        {
          "step": 22,
          "loss": 0.5571855306625366
        },
        {
          "step": 44,
          "loss": 0.47791025042533875
        },
        {
          "step": 66,
          "loss": 0.5804803371429443
        },
        {
          "step": 88,
          "loss": 0.3766342103481293
        },
        {
          "step": 110,
          "loss": 0.5511281490325928
        },
        {
          "step": 132,
          "loss": 0.6413482427597046
        },
        {
          "step": 154,
          "loss": 0.4615640640258789
        },
        {
          "step": 176,
          "loss": 0.5686454772949219
        },
        {
          "step": 198,
          "loss": 0.5514954924583435
        },
        {
          "step": 220,
          "loss": 0.5581884384155273
        }
      ],
      "val_loss": 0.430626700942715,
      "val_accuracy": 0.913874659811457,
      "train_loss": 0.5641480189832774
    },
    {
      "epoch": 11,
      "train_steps": [
        {
          "step": 22,
          "loss": 0.5414515733718872
        },
        {
          "step": 44,
          "loss": 0.4592840075492859
        },
        {
          "step": 66,
          "loss": 0.5432873964309692
        },
        {
          "step": 88,
          "loss": 0.4315286874771118
        },
        {
          "step": 110,
          "loss": 0.5305946469306946
        },
        {
          "step": 132,
          "loss": 0.497994065284729
        },
        {
          "step": 154,
          "loss": 0.6191006898880005
        },
        {
          "step": 176,
          "loss": 0.62667316198349
        },
        {
          "step": 198,
          "loss": 0.5837374329566956
        },
        {
          "step": 220,
          "loss": 0.7067141532897949
        }
      ],
      "val_loss": 0.45387691631913185,
      "val_accuracy": 0.9092246167361736,
      "train_loss": 0.54303288012743
    },
    {
      "epoch": 12,
      "train_steps": [
        {
          "step": 22,
          "loss": 0.645137369632721
        },
        {
          "step": 44,
          "loss": 0.550058126449585
        },
        {
          "step": 66,
          "loss": 0.5273176431655884
        },
        {
          "step": 88,
          "loss": 0.6413050889968872
        },
        {
          "step": 110,
          "loss": 0.5750455856323242
        },
        {
          "step": 132,
          "loss": 0.5030220150947571
        },
        {
          "step": 154,
          "loss": 0.48051995038986206
        },
        {
          "step": 176,
          "loss": 0.4835289716720581
        },
        {
          "step": 198,
          "loss": 0.45888400077819824
        },
        {
          "step": 220,
          "loss": 0.662606954574585
        }
      ],
      "val_loss": 0.43546925857663155,
      "val_accuracy": 0.9129061482846736,
      "train_loss": 0.536077751761133
    },
    {
      "epoch": 13,
      "train_steps": [
        {
          "step": 22,
          "loss": 0.430035799741745
        },
        {
          "step": 44,
          "loss": 0.5006850957870483
        },
        {
          "step": 66,
          "loss": 0.4615480303764343
        },
        {
          "step": 88,
          "loss": 0.5079467296600342
        },
        {
          "step": 110,
          "loss": 0.5296244621276855
        },
        {
          "step": 132,
          "loss": 0.5228182077407837
        },
        {
          "step": 154,
          "loss": 0.4806654453277588
        },
        {
          "step": 176,
          "loss": 0.398582398891449
        },
        {
          "step": 198,
          "loss": 0.6146581172943115
        },
        {
          "step": 220,
          "loss": 0.5990581512451172
        }
      ],
      "val_loss": 0.4605131037533283,
      "val_accuracy": 0.9078973792493343,
      "train_loss": 0.5048835349353877
    },
    {
      "epoch": 14,
      "train_steps": [
        {
          "step": 22,
          "loss": 0.5601749420166016
        },
        {
          "step": 44,
          "loss": 0.46741411089897156
        },
        {
          "step": 66,
          "loss": 0.41097044944763184
        },
        {
          "step": 88,
          "loss": 0.5280186533927917
        },
        {
          "step": 110,
          "loss": 0.7817947268486023
        },
        {
          "step": 132,
          "loss": 0.4737834334373474
        },
        {
          "step": 154,
          "loss": 0.5133188962936401
        },
        {
          "step": 176,
          "loss": 0.49577653408050537
        },
        {
          "step": 198,
          "loss": 0.4901498258113861
        },
        {
          "step": 220,
          "loss": 0.3773946762084961
        }
      ],
      "val_loss": 0.4712008213003476,
      "val_accuracy": 0.9057598357399305,
      "train_loss": 0.5064446433023972
    },
    {
      "epoch": 15,
      "train_steps": [
        {
          "step": 22,
          "loss": 0.4654109477996826
        },
        {
          "step": 44,
          "loss": 0.4035525918006897
        },
        {
          "step": 66,
          "loss": 0.6798830032348633
        },
        {
          "step": 88,
          "loss": 0.4480811059474945
        },
        {
          "step": 110,
          "loss": 0.48338836431503296
        },
        {
          "step": 132,
          "loss": 0.33700382709503174
        },
        {
          "step": 154,
          "loss": 0.4647490978240967
        },
        {
          "step": 176,
          "loss": 0.5698866844177246
        },
        {
          "step": 198,
          "loss": 0.5374751091003418
        },
        {
          "step": 220,
          "loss": 0.48071444034576416
        }
      ],
      "val_loss": 0.4442786282549302,
      "val_accuracy": 0.9111442743490139,
      "train_loss": 0.48849712325768035
    },
    {
      "epoch": 16,
      "train_steps": [
        {
          "step": 22,
          "loss": 0.4343002736568451
        },
        {
          "step": 44,
          "loss": 0.44073963165283203
        },
        {
          "step": 66,
          "loss": 0.6966435313224792
        },
        {
          "step": 88,
          "loss": 0.5228484272956848
        },
        {
          "step": 110,
          "loss": 0.35953277349472046
        },
        {
          "step": 132,
          "loss": 0.4893611669540405
        },
        {
          "step": 154,
          "loss": 0.47828420996665955
        },
        {
          "step": 176,
          "loss": 0.431525319814682
        },
        {
          "step": 198,
          "loss": 0.5053099989891052
        },
        {
          "step": 220,
          "loss": 0.4489680528640747
        }
      ],
      "val_loss": 0.4749652451525132,
      "val_accuracy": 0.9050069509694973,
      "train_loss": 0.4731136732480743
    },
    {
      "epoch": 17,
      "train_steps": [
        {
          "step": 22,
          "loss": 0.508193850517273
        },
        {
          "step": 44,
          "loss": 0.5808882117271423
        },
        {
          "step": 66,
          "loss": 0.376994252204895
        },
        {
          "step": 88,
          "loss": 0.4303208291530609
        },
        {
          "step": 110,
          "loss": 0.45229387283325195
        },
        {
          "step": 132,
          "loss": 0.3668656349182129
        },
        {
          "step": 154,
          "loss": 0.510491132736206
        },
        {
          "step": 176,
          "loss": 0.41174769401550293
        },
        {
          "step": 198,
          "loss": 0.40584301948547363
        },
        {
          "step": 220,
          "loss": 0.39545682072639465
        }
      ],
      "val_loss": 0.4480426652977864,
      "val_accuracy": 0.9103914669404427,
      "train_loss": 0.4600393306125294
    },
    {
      "epoch": 18,
      "train_steps": [
        {
          "step": 22,
          "loss": 0.6219539642333984
        },
        {
          "step": 44,
          "loss": 0.4418778419494629
        },
        {
          "step": 66,
          "loss": 0.4415777325630188
        },
        {
          "step": 88,
          "loss": 0.4761269986629486
        },
        {
          "step": 110,
          "loss": 0.45246654748916626
        },
        {
          "step": 132,
          "loss": 0.43490415811538696
        },
        {
          "step": 154,
          "loss": 0.5495760440826416
        },
        {
          "step": 176,
          "loss": 0.5815379023551941
        },
        {
          "step": 198,
          "loss": 0.32627397775650024
        },
        {
          "step": 220,
          "loss": 0.38774752616882324
        }
      ],
      "val_loss": 0.44231448508799076,
      "val_accuracy": 0.9115371029824019,
      "train_loss": 0.4567472463304346
    },
    {
      "epoch": 19,
      "train_steps": [
        {
          "step": 22,
          "loss": 0.4372710883617401
        },
        {
          "step": 44,
          "loss": 0.3974986970424652
        },
        {
          "step": 66,
          "loss": 0.5124225616455078
        },
        {
          "step": 88,
          "loss": 0.36016368865966797
        },
        {
          "step": 110,
          "loss": 0.33689308166503906
        },
        {
          "step": 132,
          "loss": 0.48421549797058105
        },
        {
          "step": 154,
          "loss": 0.3734546899795532
        },
        {
          "step": 176,
          "loss": 0.5778995752334595
        },
        {
          "step": 198,
          "loss": 0.37952959537506104
        },
        {
          "step": 220,
          "loss": 0.33656206727027893
        }
      ],
      "val_loss": 0.45827730434636277,
      "val_accuracy": 0.9083445391307274,
      "train_loss": 0.44794137464328243
    },
    {
      "epoch": 20,
      "train_steps": [
        {
          "step": 22,
          "loss": 0.37435483932495117
        },
        {
          "step": 44,
          "loss": 0.41251227259635925
        },
        {
          "step": 66,
          "loss": 0.4666319787502289
        },
        {
          "step": 88,
          "loss": 0.3347477316856384
        },
        {
          "step": 110,
          "loss": 0.4104955792427063
        },
        {
          "step": 132,
          "loss": 0.47390592098236084
        },
        {
          "step": 154,
          "loss": 0.5211713314056396
        },
        {
          "step": 176,
          "loss": 0.5169832110404968
        },
        {
          "step": 198,
          "loss": 0.4298973083496094
        },
        {
          "step": 220,
          "loss": 0.5220338106155396
        }
      ],
      "val_loss": 0.45576937062044937,
      "val_accuracy": 0.9088461258759102,
      "train_loss": 0.4310928442261436
    },
    {
      "epoch": 21,
      "train_steps": [
        {
          "step": 22,
          "loss": 0.37657541036605835
        },
        {
          "step": 44,
          "loss": 0.2839565873146057
        },
        {
          "step": 66,
          "loss": 0.4298667907714844
        },
        {
          "step": 88,
          "loss": 0.36247843503952026
        },
        {
          "step": 110,
          "loss": 0.41728124022483826
        },
        {
          "step": 132,
          "loss": 0.3934822976589203
        },
        {
          "step": 154,
          "loss": 0.5193223357200623
        },
        {
          "step": 176,
          "loss": 0.3926190733909607
        },
        {
          "step": 198,
          "loss": 0.4574943482875824
        },
        {
          "step": 220,
          "loss": 0.27056923508644104
        }
      ],
      "val_loss": 0.49272753732899827,
      "val_accuracy": 0.9014544925342003,
      "train_loss": 0.41411552293734116
    },
    {
      "epoch": 22,
      "train_steps": [
        {
          "step": 22,
          "loss": 0.3633131682872772
        },
        {
          "step": 44,
          "loss": 0.34236809611320496
        },
        {
          "step": 66,
          "loss": 0.4622369706630707
        },
        {
          "step": 88,
          "loss": 0.39953264594078064
        },
        {
          "step": 110,
          "loss": 0.3497905731201172
        },
        {
          "step": 132,
          "loss": 0.4160007834434509
        },
        {
          "step": 154,
          "loss": 0.5010094046592712
        },
        {
          "step": 176,
          "loss": 0.4859190583229065
        },
        {
          "step": 198,
          "loss": 0.4925571382045746
        },
        {
          "step": 220,
          "loss": 0.37932145595550537
        }
      ],
      "val_loss": 0.45145036342243355,
      "val_accuracy": 0.9097099273155133,
      "train_loss": 0.40744548358700494
    },
    {
      "epoch": 23,
      "train_steps": [
        {
          "step": 22,
          "loss": 0.34751981496810913
        },
        {
          "step": 44,
          "loss": 0.4030812978744507
        },
        {
          "step": 66,
          "loss": 0.4401981830596924
        },
        {
          "step": 88,
          "loss": 0.43916308879852295
        },
        {
          "step": 110,
          "loss": 0.44230741262435913
        },
        {
          "step": 132,
          "loss": 0.2989717125892639
        },
        {
          "step": 154,
          "loss": 0.3092643916606903
        },
        {
          "step": 176,
          "loss": 0.4929025173187256
        },
        {
          "step": 198,
          "loss": 0.3834075331687927
        },
        {
          "step": 220,
          "loss": 0.23930837213993073
        }
      ],
      "val_loss": 0.44767895216743153,
      "val_accuracy": 0.9104642095665136,
      "train_loss": 0.3989794630218636
    },
    {
      "epoch": 24,
      "train_steps": [
        {
          "step": 22,
          "loss": 0.403480589389801
        },
        {
          "step": 44,
          "loss": 0.36096274852752686
        },
        {
          "step": 66,
          "loss": 0.23494160175323486
        },
        {
          "step": 88,
          "loss": 0.3128204941749573
        },
        {
          "step": 110,
          "loss": 0.4310806393623352
        },
        {
          "step": 132,
          "loss": 0.4566914439201355
        },
        {
          "step": 154,
          "loss": 0.40670710802078247
        },
        {
          "step": 176,
          "loss": 0.3865036964416504
        },
        {
          "step": 198,
          "loss": 0.4357888400554657
        },
        {
          "step": 220,
          "loss": 0.393800288438797
        }
      ],
      "val_loss": 0.46307208699484664,
      "val_accuracy": 0.9073855826010306,
      "train_loss": 0.39578419903462586
    },
    {
      "epoch": 25,
      "train_steps": [
        {
          "step": 22,
          "loss": 0.528104305267334
        },
        {
          "step": 44,
          "loss": 0.3485129773616791
        },
        {
          "step": 66,
          "loss": 0.28752124309539795
        },
        {
          "step": 88,
          "loss": 0.41433605551719666
        },
        {
          "step": 110,
          "loss": 0.4352433681488037
        },
        {
          "step": 132,
          "loss": 0.46658724546432495
        },
        {
          "step": 154,
          "loss": 0.41446632146835327
        },
        {
          "step": 176,
          "loss": 0.3998781144618988
        },
        {
          "step": 198,
          "loss": 0.44966357946395874
        },
        {
          "step": 220,
          "loss": 0.4509704113006592
        }
      ],
      "val_loss": 0.4777780454605818,
      "val_accuracy": 0.9044443909078836,
      "train_loss": 0.38618266135454177
    },
    {
      "epoch": 26,
      "train_steps": [
        {
          "step": 22,
          "loss": 0.4028344750404358
        },
        {
          "step": 44,
          "loss": 0.3981647193431854
        },
        {
          "step": 66,
          "loss": 0.3434488773345947
        },
        {
          "step": 88,
          "loss": 0.3704206943511963
        },
        {
          "step": 110,
          "loss": 0.4457162618637085
        },
        {
          "step": 132,
          "loss": 0.3649802803993225
        },
        {
          "step": 154,
          "loss": 0.41725558042526245
        },
        {
          "step": 176,
          "loss": 0.4438370168209076
        },
        {
          "step": 198,
          "loss": 0.38566717505455017
        },
        {
          "step": 220,
          "loss": 0.2452930510044098
        }
      ],
      "val_loss": 0.4722424087425073,
      "val_accuracy": 0.9055515182514986,
      "train_loss": 0.3787739186124368
    },
    {
      "epoch": 27,
      "train_steps": [
        {
          "step": 22,
          "loss": 0.3815951943397522
        },
        {
          "step": 44,
          "loss": 0.33874839544296265
        },
        {
          "step": 66,
          "loss": 0.36099886894226074
        },
        {
          "step": 88,
          "loss": 0.37554189562797546
        },
        {
          "step": 110,
          "loss": 0.3951438069343567
        },
        {
          "step": 132,
          "loss": 0.3473646640777588
        },
        {
          "step": 154,
          "loss": 0.29481691122055054
        },
        {
          "step": 176,
          "loss": 0.42784398794174194
        },
        {
          "step": 198,
          "loss": 0.33872485160827637
        },
        {
          "step": 220,
          "loss": 0.2900434732437134
        }
      ],
      "val_loss": 0.4932445175945759,
      "val_accuracy": 0.9013510964810848,
      "train_loss": 0.3768322085792368
    },
    {
      "epoch": 28,
      "train_steps": [
        {
          "step": 22,
          "loss": 0.3274722993373871
        },
        {
          "step": 44,
          "loss": 0.49215835332870483
        },
        {
          "step": 66,
          "loss": 0.39234381914138794
        },
        {
          "step": 88,
          "loss": 0.3329043388366699
        },
        {
          "step": 110,
          "loss": 0.4239658713340759
        },
        {
          "step": 132,
          "loss": 0.3005281090736389
        },
        {
          "step": 154,
          "loss": 0.33216649293899536
        },
        {
          "step": 176,
          "loss": 0.34283480048179626
        },
        {
          "step": 198,
          "loss": 0.377949059009552
        },
        {
          "step": 220,
          "loss": 0.32954999804496765
        }
      ],
      "val_loss": 0.4595516671737035,
      "val_accuracy": 0.9080896665652594,
      "train_loss": 0.36601496338844297
    },
    {
      "epoch": 29,
      "train_steps": [
        {
          "step": 22,
          "loss": 0.3268700838088989
        },
        {
          "step": 44,
          "loss": 0.5638678669929504
        },
        {
          "step": 66,
          "loss": 0.4108249545097351
        },
        {
          "step": 88,
          "loss": 0.33531349897384644
        },
        {
          "step": 110,
          "loss": 0.37804290652275085
        },
        {
          "step": 132,
          "loss": 0.36092519760131836
        },
        {
          "step": 154,
          "loss": 0.27278977632522583
        },
        {
          "step": 176,
          "loss": 0.3393811881542206
        },
        {
          "step": 198,
          "loss": 0.31285351514816284
        },
        {
          "step": 220,
          "loss": 0.3343266546726227
        }
      ],
      "val_loss": 0.46854919629792374,
      "val_accuracy": 0.9062901607404152,
      "train_loss": 0.35891660045493734
    },
    {
      "epoch": 30,
      "train_steps": [
        {
          "step": 22,
          "loss": 0.38503551483154297
        },
        {
          "step": 44,
          "loss": 0.29382938146591187
        },
        {
          "step": 66,
          "loss": 0.4305514097213745
        },
        {
          "step": 88,
          "loss": 0.4021279215812683
        },
        {
          "step": 110,
          "loss": 0.29710206389427185
        },
        {
          "step": 132,
          "loss": 0.3141055405139923
        },
        {
          "step": 154,
          "loss": 0.2982957661151886
        },
        {
          "step": 176,
          "loss": 0.3245094120502472
        },
        {
          "step": 198,
          "loss": 0.400177001953125
        },
        {
          "step": 220,
          "loss": 0.35462599992752075
        }
      ],
      "val_loss": 0.46519276686012745,
      "val_accuracy": 0.9069614466279745,
      "train_loss": 0.35733800659125503
    },
    {
      "epoch": 31,
      "train_steps": [
        {
          "step": 22,
          "loss": 0.3424305319786072
        },
        {
          "step": 44,
          "loss": 0.38914960622787476
        },
        {
          "step": 66,
          "loss": 0.4558262228965759
        },
        {
          "step": 88,
          "loss": 0.26215142011642456
        },
        {
          "step": 110,
          "loss": 0.4316910207271576
        },
        {
          "step": 132,
          "loss": 0.34282463788986206
        },
        {
          "step": 154,
          "loss": 0.36136430501937866
        },
        {
          "step": 176,
          "loss": 0.29710453748703003
        },
        {
          "step": 198,
          "loss": 0.5058149099349976
        },
        {
          "step": 220,
          "loss": 0.34902840852737427
        }
      ],
      "val_loss": 0.4775218752523263,
      "val_accuracy": 0.9044956249495347,
      "train_loss": 0.3467658288099549
    },
    {
      "epoch": 32,
      "train_steps": [
        {
          "step": 22,
          "loss": 0.3202400207519531
        },
        {
          "step": 44,
          "loss": 0.440773606300354
        },
        {
          "step": 66,
          "loss": 0.45646700263023376
        },
        {
          "step": 88,
          "loss": 0.3339507579803467
        },
        {
          "step": 110,
          "loss": 0.31837594509124756
        },
        {
          "step": 132,
          "loss": 0.4470568597316742
        },
        {
          "step": 154,
          "loss": 0.3089158833026886
        },
        {
          "step": 176,
          "loss": 0.39028042554855347
        },
        {
          "step": 198,
          "loss": 0.2398979365825653
        },
        {
          "step": 220,
          "loss": 0.2589075267314911
        }
      ],
      "val_loss": 0.4733648219456275,
      "val_accuracy": 0.9053270356108745,
      "train_loss": 0.34069546549157664
    },
    {
      "epoch": 33,
      "train_steps": [
        {
          "step": 22,
          "loss": 0.2902144491672516
        },
        {
          "step": 44,
          "loss": 0.31896090507507324
        },
        {
          "step": 66,
          "loss": 0.30967459082603455
        },
        {
          "step": 88,
          "loss": 0.3848980665206909
        },
        {
          "step": 110,
          "loss": 0.3182942271232605
        },
        {
          "step": 132,
          "loss": 0.28755274415016174
        },
        {
          "step": 154,
          "loss": 0.3399089276790619
        },
        {
          "step": 176,
          "loss": 0.44433873891830444
        },
        {
          "step": 198,
          "loss": 0.3890521228313446
        },
        {
          "step": 220,
          "loss": 0.5008277893066406
        }
      ],
      "val_loss": 0.5209204691151778,
      "val_accuracy": 0.8958159061769645,
      "train_loss": 0.345640041814609
    },
    {
      "epoch": 34,
      "train_steps": [
        {
          "step": 22,
          "loss": 0.32055240869522095
        },
        {
          "step": 44,
          "loss": 0.2807846963405609
        },
        {
          "step": 66,
          "loss": 0.3242449462413788
        },
        {
          "step": 88,
          "loss": 0.20674368739128113
        },
        {
          "step": 110,
          "loss": 0.3317564129829407
        },
        {
          "step": 132,
          "loss": 0.5133861899375916
        },
        {
          "step": 154,
          "loss": 0.2064233273267746
        },
        {
          "step": 176,
          "loss": 0.32859426736831665
        },
        {
          "step": 198,
          "loss": 0.43661320209503174
        },
        {
          "step": 220,
          "loss": 0.21385762095451355
        }
      ],
      "val_loss": 0.47277843207120895,
      "val_accuracy": 0.9054443135857582,
      "train_loss": 0.3287976659834385
    },
    {
      "epoch": 35,
      "train_steps": [
        {
          "step": 22,
          "loss": 0.2999548614025116
        },
        {
          "step": 44,
          "loss": 0.3097337484359741
        },
        {
          "step": 66,
          "loss": 0.3101648688316345
        },
        {
          "step": 88,
          "loss": 0.3030487298965454
        },
        {
          "step": 110,
          "loss": 0.5323818922042847
        },
        {
          "step": 132,
          "loss": 0.2728215754032135
        },
        {
          "step": 154,
          "loss": 0.4573555588722229
        },
        {
          "step": 176,
          "loss": 0.3160122334957123
        },
        {
          "step": 198,
          "loss": 0.3976399302482605
        },
        {
          "step": 220,
          "loss": 0.41329437494277954
        }
      ],
      "val_loss": 0.4708259745190541,
      "val_accuracy": 0.9058348050961892,
      "train_loss": 0.32851306288079785
    },
    {
      "epoch": 36,
      "train_steps": [
        {
          "step": 22,
          "loss": 0.339120090007782
        },
        {
          "step": 44,
          "loss": 0.26412433385849
        },
        {
          "step": 66,
          "loss": 0.34491050243377686
        },
        {
          "step": 88,
          "loss": 0.38744041323661804
        },
        {
          "step": 110,
          "loss": 0.2700656056404114
        },
        {
          "step": 132,
          "loss": 0.3377719819545746
        },
        {
          "step": 154,
          "loss": 0.3651815354824066
        },
        {
          "step": 176,
          "loss": 0.37414106726646423
        },
        {
          "step": 198,
          "loss": 0.3507557809352875
        },
        {
          "step": 220,
          "loss": 0.3431145250797272
        }
      ],
      "val_loss": 0.46653211240967113,
      "val_accuracy": 0.9066935775180658,
      "train_loss": 0.32453321638432414
    },
    {
      "epoch": 37,
      "train_steps": [
        {
          "step": 22,
          "loss": 0.2917613089084625
        },
        {
          "step": 44,
          "loss": 0.4371301829814911
        },
        {
          "step": 66,
          "loss": 0.3296082019805908
        },
        {
          "step": 88,
          "loss": 0.34868285059928894
        },
        {
          "step": 110,
          "loss": 0.3252643644809723
        },
        {
          "step": 132,
          "loss": 0.27995049953460693
        },
        {
          "step": 154,
          "loss": 0.32587775588035583
        },
        {
          "step": 176,
          "loss": 0.41221103072166443
        },
        {
          "step": 198,
          "loss": 0.284618079662323
        },
        {
          "step": 220,
          "loss": 0.18954487144947052
        }
      ],
      "val_loss": 0.48157638621826965,
      "val_accuracy": 0.903684722756346,
      "train_loss": 0.31404041505672714
    },
    {
      "epoch": 38,
      "train_steps": [
        {
          "step": 22,
          "loss": 0.3904820382595062
        },
        {
          "step": 44,
          "loss": 0.3019486665725708
        },
        {
          "step": 66,
          "loss": 0.3572794198989868
        },
        {
          "step": 88,
          "loss": 0.3350828289985657
        },
        {
          "step": 110,
          "loss": 0.3025272488594055
        },
        {
          "step": 132,
          "loss": 0.24839571118354797
        },
        {
          "step": 154,
          "loss": 0.2644408941268921
        },
        {
          "step": 176,
          "loss": 0.38532477617263794
        },
        {
          "step": 198,
          "loss": 0.33271315693855286
        },
        {
          "step": 220,
          "loss": 0.21855728328227997
        }
      ],
      "val_loss": 0.49860066672166187,
      "val_accuracy": 0.9002798666556676,
      "train_loss": 0.3156810755079443
    },
    {
      "epoch": 39,
      "train_steps": [
        {
          "step": 22,
          "loss": 0.27744489908218384
        },
        {
          "step": 44,
          "loss": 0.32620713114738464
        },
        {
          "step": 66,
          "loss": 0.28871166706085205
        },
        {
          "step": 88,
          "loss": 0.26188379526138306
        },
        {
          "step": 110,
          "loss": 0.28668779134750366
        },
        {
          "step": 132,
          "loss": 0.2505846619606018
        },
        {
          "step": 154,
          "loss": 0.3186495900154114
        },
        {
          "step": 176,
          "loss": 0.286776602268219
        },
        {
          "step": 198,
          "loss": 0.23617681860923767
        },
        {
          "step": 220,
          "loss": 0.2643786668777466
        }
      ],
      "val_loss": 0.4732314186791579,
      "val_accuracy": 0.9053537162641684,
      "train_loss": 0.31159413023428484
    },
    {
      "epoch": 40,
      "train_steps": [
        {
          "step": 22,
          "loss": 0.28411269187927246
        },
        {
          "step": 44,
          "loss": 0.304770290851593
        },
        {
          "step": 66,
          "loss": 0.2497139424085617
        },
        {
          "step": 88,
          "loss": 0.24378632009029388
        },
        {
          "step": 110,
          "loss": 0.3453316390514374
        },
        {
          "step": 132,
          "loss": 0.30178362131118774
        },
        {
          "step": 154,
          "loss": 0.28342312574386597
        },
        {
          "step": 176,
          "loss": 0.2864855229854584
        },
        {
          "step": 198,
          "loss": 0.33248335123062134
        },
        {
          "step": 220,
          "loss": 0.29658639430999756
        }
      ],
      "val_loss": 0.4836363438516855,
      "val_accuracy": 0.9032727312296629,
      "train_loss": 0.30993996770544485
    }
  ],
  "audio_feature": "spectrogram",
  "fusion_type": "early"
}